Workbook

Sheet 635
B1: 635 | L1: Full payment | P1: 635 RECEIVABLE FROM ATE CZARINA
B2: Date | E2: Amount | F2: Parking | G2: Agent's Commissions | H2: Remarks | I2: Reservation | K2: Balance | O2: Cleaning Fee | P2: Others | Q2: Receivable Balance | R2: Remarks
I3: Gcash | J3: BDO | L3: BDO | M3: GCASH | N3: Ate CZARINA
B4: Feb | C4: 45941 | D4: 1 | E4: 2000 | I4: 1000 | K4: =E4-I4-L4-M4-N4-J4+F4 -> 0 | N4: 1000 | O4: -500 | Q4: =N4+O4+P4 -> 500
C5: 13-14 | D5: 1 | E5: 2300 | I5: 1000 | K5: =E5-I5-L5-M5-N5-J5+F5 -> 0 | N5: 1300 | O5: -500 | Q5: =Q4+N5+O5+P5 -> 1300
C6: 14-15 | D6: 1 | E6: 2600 | G6: -300 | I6: 500 | K6: =E6-I6-L6-M6-N6-J6+F6 -> 0 | N6: 2100 | O6: -500 | Q6: =Q5+N6+O6+P6 -> 2900
C7: 15-17 | D7: 2 | E7: 5300 | I7: 1500 | K7: =E7-I7-L7-M7-N7-J7+F7 -> 0 | N7: 3800 | O7: -500 | Q7: =Q6+N7+O7+P7 -> 6200
C8: 17-19 | D8: 2 | E8: =4200+1800 -> 6000 | G8: -800 | K8: =E8-I8-L8-M8-N8-J8+F8 -> 0 | M8: 1800 | N8: 4200 | O8: -500 | Q8: =Q7+N8+O8+P8 -> 9900
C9: 19-21 | K9: =E9-I9-L9-M9-N9-J9+F9 -> 0 | Q9: =Q8+N9+O9+P9 -> 9900
C10: 21-22 | D10: 1 | E10: 3350 | F10: 450 | I10: 1450 | K10: =E10-I10-L10-M10-N10-J10+F10 -> 0 | N10: 2350 | O10: -500 | Q10: =Q9+N10+O10+P10 -> 11750
C11: 22-24 | D11: 2 | E11: 4800 | I11: 1300 | K11: =E11-I11-L11-M11-N11-J11+F11 -> 0 | N11: 3500 | O11: -500 | Q11: =Q10+N11+O11+P11 -> 14750
C12: 24-25 | D12: 1 | E12: =2100+350 -> 2450 | I12: 600 | K12: =E12-I12-L12-M12-N12-J12+F12 -> 0 | M12: 1850 | O12: -500 | Q12: =Q11+N12+O12+P12 -> 14250
C13: 25-26 | K13: =E13-I13-L13-M13-N13-J13+F13 -> 0 | Q13: =Q12+N13+O13+P13 -> 14250
C14: 26-27 | D14: 1 | E14: 2650 | I14: 1000 | K14: =E14-I14-L14-M14-N14-J14+F14 -> 0 | N14: 1650 | O14: -500 | Q14: =Q13+N14+O14+P14 -> 15400
C15: 27-28 | K15: =E15-I15-L15-M15-N15-J15+F15 -> 0 | Q15: =Q14+N15+O15+P15 -> 15400
C16: 28-1 | D16: 1 | E16: 2300 | I16: 500 | K16: =E16-I16-L16-M16-N16-J16+F16 -> 0 | M16: 800 | N16: 1000 | O16: -500 | Q16: =Q15+N16+O16+P16 -> 15900
P17: -500 | Q17: =Q16+N17+O17+P17 -> 15400 | R17: General cleaning
P18: -500 | Q18: =Q17+N18+O18+P18 -> 14900 | R18: Laundry
K19: =E19-I19-L19-M19-N19-J19+F19 -> 0 | P19: =-1500+-300 -> -1800 | Q19: =Q18+N19+O19+P19 -> 13100 | R19: heater repair
K20: =E20-I20-L20-M20-N20-J20+F20 -> 0 | P20: -695.5 | Q20: =Q19+N20+O20+P20 -> 12404.5 | R20: supplies
P21: -12404.5 | Q21: =Q20+N21+O21+P21 -> 0
B22: Feb | C22: Total | D22: =sum(D4:D19) -> 13 | E22: =sum(E4:E19) -> 33750 | G22: =sum(G4:G19) -> -1100 | I22: =sum(I4:I19) -> 8850 | J22: =sum(J4:J19) -> 0 | K22: =sum(K4:K19) -> 0 | L22: =sum(L4:L19) -> 0 | M22: =sum(M4:M19) -> 4450 | N22: =sum(N4:N19) -> 20900 | O22: =sum(O4:O19) -> -5000 | P22: =sum(P4:P19) -> -2800 | Q22: =Q21 -> 0
B23: Mar | C23: 45659 | D23: 1 | E23: 3750 | I23: 1000 | K23: =E23-I23-L23-M23-N23-J23+F23 -> 0 | N23: 2750 | O23: -500 | Q23: =N23+O23+P23 -> 2250
C24: 45691 | D24: 1 | E24: =2600+350 -> 2950 | J24: 1200 | K24: =E24-I24-L24-M24-N24-J24+F24 -> 0 | N24: 1750 | O24: -500 | Q24: =Q23+N24+O24+P24 -> 3500
C25: 45721 | K25: =E25-I25-L25-M25-N25-J25+F25 -> 0 | Q25: =Q24+N25+O25+P25 -> 3500
C26: 45783 | D26: 1 | E26: 2000 | I26: 800 | K26: =E26-I26-L26-M26-N26-J26+F26 -> 0 | N26: 1200 | O26: -500 | Q26: =Q25+N26+O26+P26 -> 4200
C27: 45816 | D27: 2 | E27: 3240.1 | H27: airbnb | K27: =E27-I27-L27-M27-N27-J27+F27 -> 0 | L27: 3240.1 | O27: -500 | Q27: =Q26+N27+O27+P27 -> 3700
C28: 45878 | D28: 1 | E28: 3500 | I28: 1000 | K28: =E28-I28-L28-M28-N28-J28+F28 -> 0 | N28: 2500 | O28: -500 | Q28: =Q27+N28+O28+P28 -> 5700
C29: 45910 | K29: =E29-I29-L29-M29-N29-J29+F29 -> 0 | Q29: =Q28+N29+O29+P29 -> 5700
C30: 45941 | D30: 1 | E30: =2100 -> 2100 | F30: 350 | I30: 950 | K30: =E30-I30-L30-M30-N30-J30+F30 -> 0 | N30: 1500 | O30: -500 | Q30: =Q29+N30+O30+P30 -> 6700
C31: 45975 | K31: =E31-I31-L31-M31-N31-J31+F31 -> 0 | Q31: =Q30+N31+O31+P31 -> 6700
C32: 15-16 | D32: 1 | E32: 3000 | I32: 500 | K32: =E32-I32-L32-M32-N32-J32+F32 -> 0 | N32: 2500 | O32: -500 | Q32: =Q31+N32+O32+P32 -> 8700
C33: 16-17 | D33: 1 | E33: 2500 | I33: 1000 | K33: =E33-I33-L33-M33-N33-J33+F33 -> 0 | N33: 1500 | O33: -500 | Q33: =Q32+N33+O33+P33 -> 9700
C34: 17-19 | D34: 2 | E34: 3500 | I34: 1500 | K34: =E34-I34-L34-M34-N34-J34+F34 -> 0 | N34: 2000 | O34: -500 | Q34: =Q33+N34+O34+P34 -> 11200
C35: 19-21 | K35: =E35-I35-L35-M35-N35-J35+F35 -> 0 | O35: -500 | Q35: =Q34+N35+O35+P35 -> 10700 | R35: Jaykath (Mar 21)
C36: 22-23 | D36: 1 | E36: 3500 | I36: 700 | K36: =E36-I36-L36-M36-N36-J36+F36 -> 0 | N36: 2800 | O36: -500 | Q36: =Q35+N36+O36+P36 -> 13000
C37: 23-26 | D37: 3 | E37: =4899+1000 -> 5899 | G37: -899 | I37: 1000 | K37: =E37-I37-L37-M37-N37-J37+F37 -> 0 | N37: 4899 | O37: -500 | Q37: =Q36+N37+O37+P37 -> 17399
C38: 26-27 | K38: =E38-I38-L38-M38-N38-J38+F38 -> 0 | Q38: =Q37+N38+O38+P38 -> 17399
C39: 27-28 | D39: 1 | E39: 2400 | I39: 1500 | K39: =E39-I39-L39-M39-N39-J39+F39 -> 0 | M39: 900 | O39: -500 | Q39: =Q38+N39+O39+P39 -> 16899
C40: 28-29 | E40: 1000 | H40: forfeited | I40: 1000 | K40: =E40-I40-L40-M40-N40-J40+F40 -> 0 | Q40: =Q39+N40+O40+P40 -> 16899
C41: 29-30 | D41: 1 | E41: 1900 | I41: 1000 | K41: =E41-I41-L41-M41-N41-J41+F41 -> 0 | N41: 900 | O41: -500 | Q41: =Q40+N41+O41+P41 -> 17299
C42: 30-31 | K42: =E42-I42-L42-M42-N42-J42+F42 -> 0 | Q42: =Q41+N42+O42+P42 -> 17299
C43: 31-2 | D43: 2 | E43: 3900 | I43: 900 | K43: =E43-I43-L43-M43-N43-J43+F43 -> 0 | N43: 3000 | O43: -500 | Q43: =Q42+N43+O43+P43 -> 19799
P44: -1059.8 | Q44: =Q43+N44+O44+P44 -> 18739.2 | R44: water
P45: -105 | Q45: =Q44+N45+O45+P45 -> 18634.2 | R45: bidet replace
P46: -103 | Q46: =Q45+N46+O46+P46 -> 18531.2 | R46: bulb
P47: -500 | Q47: =Q46+N47+O47+P47 -> 18031.2 | R47: grease trap
P48: -18031.2 | Q48: =Q47+N48+O48+P48 -> 0
B49: Mar | C49: Total | D49: =sum(D23:D44) -> 19 | E49: =sum(E23:E44) -> 45139.1 | F49: =sum(F23:F44) -> 350 | G49: =sum(G23:G44) -> -899 | H49: =sum(H23:H44) -> 0 | I49: =sum(I23:I44) -> 12850 | J49: =sum(J23:J44) -> 1200 | K49: =sum(K23:K44) -> 0 | ... P49: =sum(P23:P44) -> -1059.8 | Q49: =Q48 -> 0
B50: Apr | C50: 45693 | K50: =E50-I50-L50-M50-N50-J50+F50 -> 0 | Q50: =Q49 -> 0
B51: Apr | C51: 45783 | D51: 1 | E51: 3400 | I51: 1000 | K51: =E51-I51-L51-M51-N51-J51+F51 -> 0 | M51: 2400 | O51: -500 | Q51: =Q50+N51+O51+P51 -> -500 | R51: check | S51: che limjuco
C52: 45816 | D52: 2 | E52: 5000 | I52: 1000 | K52: =E52-I52-L52-M52-N52-J52+F52 -> 0 | N52: 4000 | O52: -500 | Q52: =Q51+N52+O52+P52 -> 3000
C53: 45878 | D53: 1 | E53: =2400+800 -> 3200 | I53: 1000 | K53: =E53-I53-L53-M53-N53-J53+F53 -> 0 | N53: 2200 | O53: -500 | Q53: =Q52+N53+O53+P53 -> 4700
C54: 45910 | K54: =E54-I54-L54-M54-N54-J54+F54 -> 0 | Q54: =Q53+N54+O54+P54 -> 4700
C55: 45942 | D55: 2 | E55: 5200 | I55: 1500 | K55: =E55-I55-L55-M55-N55-J55+F55 -> 0 | N55: 3700 | O55: -500 | Q55: =Q54+N55+O55+P55 -> 7900
C56: 46004 | D56: 1 | E56: 3800 | I56: 1000 | K56: =E56-I56-L56-M56-N56-J56+F56 -> 0 | N56: 2800 | O56: -500 | Q56: =Q55+N56+O56+P56 -> 10200
C57: 13-15 | D57: 2 | E57: 5000 | I57: 1500 | K57: =E57-I57-L57-M57-N57-J57+F57 -> 0 | N57: 3500 | O57: -500 | Q57: =Q56+N57+O57+P57 -> 13200
C58: 15-16 | K58: =E58-I58-L58-M58-N58-J58+F58 -> 0 | Q58: =Q57+N58+O58+P58 -> 13200
C59: 16-17 | D59: 1 | E59: 2550 | I59: 650 | K59: =E59-I59-L59-M59-N59-J59+F59 -> 0 | M59: 1900 | O59: -500 | Q59: =Q58+N59+O59+P59 -> 12700 | R59: check | S59: emely moran
C60: 16-17 | E60: 1000 | H60: cancelled | I60: 1000 | K60: =E60-I60-L60-M60-N60-J60+F60 -> 0 | Q60: =Q59+N60+O60+P60 -> 12700 | R60: cancelled
C61: 17-18 | D61: 1 | E61: 2800 | I61: 1000 | K61: =E61-I61-L61-M61-N61-J61+F61 -> 0 | N61: 1800 | O61: -500 | Q61: =Q60+N61+O61+P61 -> 14000
C62: 18-19 | D62: 1 | E62: 3200 | F62: 400 | I62: 1200 | K62: =E62-I62-L62-M62-N62-J62+F62 -> 0 | N62: 2400 | O62: -500 | Q62: =Q61+N62+O62+P62 -> 15900
C63: 19-21 | D63: 2 | E63: 4074 | K63: =E63-I63-L63-M63-N63-J63+F63 -> 0 | L63: 4074 | O63: -500 | Q63: =Q62+N63+O63+P63 -> 15400
C64: 21-22 | D64: 1 | E64: 2550 | I64: 500 | K64: =E64-I64-L64-M64-N64-J64+F64 -> 0 | N64: 2050 | O64: -500 | Q64: =Q63+N64+O64+P64 -> 16950
C65: 22-23 | D65: 1 | E65: =2700 -> 2700 | F65: 450 | J65: 1200 | K65: =E65-I65-L65-M65-N65-J65+F65 -> 0 | N65: 1950 | O65: -500 | Q65: =Q64+N65+O65+P65 -> 18400
C66: 23-24 | D66: 1 | E66: 3300 | F66: 350 | I66: 1350 | K66: =E66-I66-L66-M66-N66-J66+F66 -> 0 | M66: 2300 | O66: -500 | Q66: =Q65+N66+O66+P66 -> 17900
C67: 24-25 | E67: 1500 | K67: =E67-I67-L67-M67-N67-J67+F67 -> 0 | M67: 1500 | Q67: =Q66+N67+O67+P67 -> 17900 | R67: exted
C68: 25-26 | K68: =E68-I68-L68-M68-N68-J68+F68 -> 0 | Q68: =Q67+N68+O68+P68 -> 17900
C69: 26-27 | D69: 1 | E69: 3102.25 | K69: =E69-I69-L69-M69-N69-J69+F69 -> 0 | L69: 3102.25 | O69: -500 | Q69: =Q68+N69+O69+P69 -> 17400
C70: 27-28 | K70: =E70-I70-L70-M70-N70-J70+F70 -> 0 | Q70: =Q69+N70+O70+P70 -> 17400
C71: 28-1 | D71: 3 | E71: =6100+2800 -> 8900 | I71: 1500 | K71: =E71-I71-L71-M71-N71-J71+F71 -> 0 | N71: =4600+2800 -> 7400 | O71: -500 | Q71: =Q70+N71+O71+P71 -> 24300
K72: =E72-I72-L72-M72-N72-J72+F72 -> 0 | P72: -955.32 | Q72: =Q71+N72+O72+P72 -> 23344.68 | R72: water
K73: =E73-I73-L73-M73-N73-J73+F73 -> 0 | P73: -23344.68 | Q73: =Q72+N73+O73+P73 -> 0
B74: Apr | C74: Total | D74: =sum(D50:D72) -> 21 | E74: =sum(E50:E72) -> 61276.25 | F74: =sum(F50:F72) -> 1200 | G74: =sum(G50:G72) -> 0 | H74: =sum(H50:H72) -> 0 | I74: =sum(I50:I72) -> 14200 | J74: =sum(J50:J72) -> 1200 | K74: =sum(K50:K72) -> 0 | ... O74: =sum(O50:O72) -> -7500 | P74: =sum(P50:P73) -> -24300 | Q74: =Q73 -> 0
B75: May | C75: 45659 | D75: 1 | E75: 2689.81 | H75: airbnb | K75: =E75-I75-L75-M75-N75-J75+F75 -> 0 | L75: 2689.81 | O75: -500 | Q75: =Q74+N75+O75+P75 -> -500 | S75: che limjuco
C76: 45691 | D76: 1 | E76: 2400 | I76: 500 | K76: =E76-I76-L76-M76-N76-J76+F76 -> 0 | N76: 1900 | O76: -500 | Q76: =Q75+N76+O76+P76 -> 900 | S76: che limjuco
C77: 45720 | D77: 1 | E77: 3500 | I77: 1500 | K77: =E77-I77-L77-M77-N77-J77+F77 -> 0 | N77: 2000 | O77: -500 | Q77: =Q76+N77+O77+P77 -> 2400
C78: 45756 | K78: =E78-I78-L78-M78-N78-J78+F78 -> 0 | Q78: =Q77+N78+O78+P78 -> 2400
C79: 45910 | D79: 1 | E79: 2100 | I79: 501 | K79: =E79-I79-L79-M79-N79-J79+F79 -> 0 | N79: 1599 | O79: -500 | Q79: =Q78+N79+O79+P79 -> 3499
C80: 45941 | D80: 1 | E80: 3750 | G80: -500 | K80: =E80-I80-L80-M80-N80-J80+F80+G81 -> 0 | N80: 3750 | O80: -500 | Q80: =Q79+N80+O80+P80 -> 6749
C81: 45973 | D81: 1 | E81: 2537.23 | H81: airbnb | K81: =E81-I81-L81-M81-N81-J81+F81 -> 0 | L81: 2537.23 | O81: -500 | Q81: =Q80+N81+O81+P81 -> 6249
C82: 46005 | K82: =E82-I82-L82-M82-N82-J82+F82 -> 0 | Q82: =Q81+N82+O82+P82 -> 6249
C83: 14-15 | D83: 1 | E83: 2450 | I83: 1000 | K83: =E83-I83-L83-M83-N83-J83+F83 -> 0 | N83: 1450 | O83: -500 | Q83: =Q82+N83+O83+P83 -> 7199 | S83: emely moran
C84: 15-17 | K84: =E84-I84-L84-M84-N84-J84+F84 -> 0 | Q84: =Q83+N84+O84+P84 -> 7199
C85: 17-18 | D85: 1 | E85: 3000 | G85: -200 | I85: 1000 | K85: =E85-I85-L85-M85-N85-J85+F85 -> 0 | N85: 2000 | O85: -500 | Q85: =Q84+N85+O85+P85 -> 8699
C86: 18-19 | K86: =E86-I86-L86-M86-N86-J86+F86 -> 0 | Q86: =Q85+N86+O86+P86 -> 8699
C87: 19-21 | D87: 2 | E87: =400+4300-950 -> 3750 | I87: 1500 | K87: =E87-I87-L87-M87-N87-J87+F87 -> 0 | N87: =3200-950 -> 2250 | O87: -500 | Q87: =Q86+N87+O87+P87 -> 10449
C88: 21-23 | D88: 2 | E88: 4000 | K88: =E88-I88-L88-M88-N88-J88+F88 -> 0 | N88: 4000 | O88: -500 | Q88: =Q87+N88+O88+P88 -> 13949
C89: 23-24 | D89: 1 | E89: 3200 | I89: 1000 | K89: =E89-I89-L89-M89-N89-J89+F89 -> 0 | N89: 2200 | O89: -500 | Q89: =Q88+N89+O89+P89 -> 15649
C90: 24-25 | D90: 1 | E90: 3500 | I90: 1000 | K90: =E90-I90-L90-M90-N90-J90+F90 -> 0 | N90: 2500 | O90: -500 | Q90: =Q89+N90+O90+P90 -> 17649
C91: 25-26 | D91: 1 | E91: 2537.23 | K91: =E91-I91-L91-M91-N91-J91+F91 -> 0 | L91: 2537.23 | O91: -500 | Q91: =Q90+N91+O91+P91 -> 17149
C92: 26-27 | D92: 1 | E92: 2300 | I92: 1000 | K92: =E92-I92-L92-M92-N92-J92+F92 -> 0 | N92: 1300 | O92: -500 | Q92: =Q91+N92+O92+P92 -> 17949
C93: 27-30 | K93: =E93-I93-L93-M93-N93-J93+F93 -> 0 | Q93: =Q92+N93+O93+P93 -> 17949
C94: 30-31 | D94: 1 | E94: 2200 | K94: =E94-I94-L94-M94-N94-J94+F94 -> 0 | N94: 2200 | O94: -500 | Q94: =Q93+N94+O94+P94 -> 19649
C95: 31-1 | D95: 1 | E95: 2300 | I95: 2300 | K95: =E95-I95-L95-M95-N95-J95+F95 -> 0 | O95: -500 | P95: -19149 | Q95: =Q94+N95+O95+P95 -> 0
B96: May | C96: Total | D96: =sum(D75:D95) -> 18 | E96: =sum(E75:E95) -> 46214.27 | F96: =sum(F75:F95) -> 0 | G96: =sum(G75:G95) -> -700 | H96: =sum(H75:H95) -> 0 | I96: =sum(I75:I95) -> 11301 | J96: =sum(J75:J95) -> 0 | K96: =sum(K75:K95) -> 0 | ... P96: =sum(P75:P95) -> -19149 | Q96: =Q95 -> 0
B97: Jun | C97: 45659 | K97: =E97-I97-L97-M97-N97-J97+F97 -> 0 | Q97: =Q96+N97+O97+P97 -> 0
C98: 45721 | D98: 2 | E98: 4900 | F98: 900 | I98: =1500+450 -> 1950 | K98: =E98-I98-L98-M98-N98-J98+F98 -> 0 | N98: 3850 | O98: -500 | Q98: =Q97+N98+O98+P98 -> 3350
C99: 45783 | K99: =E99-I99-L99-M99-N99-J99+F99 -> 0 | Q99: =Q98+N99+O99+P99 -> 3350
C100: 45815 | D100: 1 | E100: 3100 | G100: -500 | I100: 501 | K100: =E100-I100-L100-M100-N100-J100+F100 -> 0 | N100: 2599 | O100: -500 | Q100: =Q99+N100+O100+P100 -> 5449
...

Sheet 1931
B1: 1931 BOOKING | L1: Full payment | P1: 1931 RECEIVABLE FROM ATE CZARINA
B2: Date | E2: Amount | F2: Parking | G2: Agent's Commissions | H2: Remarks | I2: Reservation | K2: Balance | O2: Cleaning Fee | P2: Others | Q2: Receivable Balance | R2: Remarks
I3: Gcash | J3: BDO | L3: BDO | M3: GCASH | N3: Ate CZARINA
B4: Jan | C4: 45691 | D4: 1 | E4: 2000 | F4: 450 | I4: 1200 | K4: =E4-I4-L4-M4-N4-J4+F4 -> 0 | M4: 1250 | O4: -500 | Q4: =N4+O4+P4 -> -500
C5: 3-4 | D5: 1 | E5: 2000 | I5: 1000 | K5: =E5-I5-L5-M5-N5-J5+F5 -> 0 | N5: 1000 | O5: -500 | Q5: =Q4+N5+O5+P5 -> 0
C6: 45752 | D6: 1 | E6: 3000 | F6: 450 | G6: =50+400 -> 450 | I6: 1000 | K6: =E6-I6-L6-M6-N6-J6+F6 -> 0 | N6: 2450 | O6: -500 | Q6: =Q5+N6+O6+P6 -> 1950
C7: 5-8 | K7: =E7-I7-L7-M7-N7-J7+F7 -> 0 | Q7: =Q6+N7+O7+P7 -> 1950
C8: 8-9 | D8: 1 | E8: 2000 | I8: 1000 | K8: =E8-I8-L8-M8-N8-J8+F8 -> 0 | N8: 1000 | O8: -500 | Q8: =Q7+N8+O8+P8 -> 2450
C9: 45910 | D9: 1 | E9: 2000 | I9: 1000 | K9: =E9-I9-L9-M9-N9-J9+F9 -> 0 | N9: 1000 | O9: -500 | Q9: =Q8+N9+O9+P9 -> 2950
C10: 45941 | D10: 1 | E10: 2300 | I10: 1000 | K10: =E10-I10-L10-M10-N10-J10+F10 -> 0 | N10: 1300 | O10: -500 | Q10: =Q9+N10+O10+P10 -> 3750
C11: 45973 | D11: 1 | E11: =2500+400 -> 2900 | I11: 1000 | K11: =E11-I11-L11-M11-N11-J11+F11 -> 0 | N11: 1900 | O11: -500 | Q11: =Q10+N11+O11+P11 -> 5150
C12: 46005 | K12: =E12-I12-L12-M12-N12-J12+F12 -> 0 | Q12: =Q11+N12+O12+P12 -> 5150
C13: 14-15 | D13: 1 | E13: 2200 | G13: 400 | I13: 1000 | K13: =E13-I13-L13-M13-N13-J13+F13 -> 0 | N13: 1200 | O13: -500 | Q13: =Q12+N13+O13+P13 -> 5850
C14: 15-16 | D14: 1 | E14: 1800 | I14: 1000 | K14: =E14-I14-L14-M14-N14-J14+F14 -> 0 | N14: 800 | O14: -500 | Q14: =Q13+N14+O14+P14 -> 6150
C15: 16-17 | D15: 1 | E15: 1800 | I15: 1000 | K15: =E15-I15-L15-M15-N15-J15+F15 -> 0 | M15: 800 | O15: -500 | Q15: =Q14+N15+O15+P15 -> 5650
C16: 17-18 | D16: 1 | E16: 2300 | I16: 1000 | K16: =E16-I16-L16-M16-N16-J16+F16 -> 0 | N16: 1300 | O16: -500 | Q16: =Q15+N16+O16+P16 -> 6450
C17: 18-19 | D17: 1 | E17: 2500 | I17: 1000 | K17: =E17-I17-L17-M17-N17-J17+F17 -> 0 | N17: 1500 | O17: -500 | Q17: =Q16+N17+O17+P17 -> 7450
C18: 19-20 | K18: =E18-I18-L18-M18-N18-J18+F18 -> 0 | Q18: =Q17+N18+O18+P18 -> 7450
C19: 20-22 | D19: 2 | E19: 3500 | I19: 1500 | K19: =E19-I19-L19-M19-N19-J19+F19 -> 0 | N19: 2000 | O19: -500 | Q19: =Q18+N19+O19+P19 -> 8950
C20: 22-23 | K20: =E20-I20-L20-M20-N20-J20+F20 -> 0 | Q20: =Q19+N20+O20+P20 -> 8950
C21: 23-24 | D21: 1 | E21: 2000 | I21: 1000 | K21: =E21-I21-L21-M21-N21-J21+F21 -> 0 | N21: 1000 | O21: -500 | Q21: =Q20+N21+O21+P21 -> 9450
C22: 24-25 | D22: 1 | E22: 2300 | I22: 1000 | K22: =E22-I22-L22-M22-N22-J22+F22 -> 0 | N22: 1300 | O22: -500 | Q22: =Q21+N22+O22+P22 -> 10250
C23: 25-26 | D23: 1 | E23: 2500 | I23: 500 | K23: =E23-I23-L23-M23-N23-J23+F23 -> 0 | N23: 2000 | O23: -500 | Q23: =Q22+N23+O23+P23 -> 11750
C24: 26-27 | D24: 1 | E24: 1900 | G24: 100 | K24: =E24-I24-L24-M24-N24-J24+F24 -> 0 | N24: 1900 | O24: -500 | Q24: =Q23+N24+O24+P24 -> 13150
C25: 27-29 | D25: 2 | E25: 3500 | I25: 1500 | K25: =E25-I25-L25-M25-N25-J25+F25 -> 0 | N25: 2000 | O25: -500 | Q25: =Q24+N25+O25+P25 -> 14650
C26: 29-30 | D26: 1 | E26: 2500 | I26: 1000 | K26: =E26-I26-L26-M26-N26-J26+F26 -> 0 | N26: 1500 | O26: -500 | Q26: =Q25+N26+O26+P26 -> 15650
C27: 30-31 | K27: =E27-I27-L27-M27-N27-J27+F27 -> 0 | Q27: =Q26+N27+O27+P27 -> 15650 | U27: 58080.36
C28: 31-1 | D28: 1 | E28: 1600 | I28: 500 | K28: =E28-I28-L28-M28-N28-J28+F28 -> 0 | N28: 1100 | O28: -500 | Q28: =Q27+N28+O28+P28 -> 16250 | U28: =U27-27368 -> 30712.36
P29: -2954.41 | Q29: =Q28+N29+O29+P29 -> 13295.59 | R29: Meralco
P30: -5472.35 | Q30: =Q29+N30+O30+P30 -> 7823.24 | R30: Association dues
K31: =E31-I31-L31-M31-N31-J31+F31 -> 0 | P31: -1627.64 | Q31: =Q30+N31+O31+P31 -> 6195.6 | R31: Airfryer
K32: =E32-I32-L32-M32-N32-J32+F32 -> 0 | P32: -2800 | Q32: =Q31+N32+O32+P32 -> 3395.6 | R32: Decor
P33: =-6195+2799 -> -3396 | Q33: =Q32+N33+O33+P33 -> -0.4 | R33: Remittance
B34: Jan | C34: Total | D34: =sum(D4:D31) -> 22 | E34: =sum(E4:E31) -> 46600 | G34: =sum(G4:G31) -> 950 | I34: =sum(I4:I31) -> 19200 | J34: =sum(J4:J31) -> 0 | K34: =sum(K4:K31) -> 0 | L34: =sum(L4:L31) -> 0 | M34: =sum(M4:M31) -> 2050 | N34: =sum(N4:N31) -> 26250 | O34: =sum(O4:O31) -> -10000 | P34: =sum(P4:P31) -> -10054.4 | Q34: =Q33 -> -0.4
B35: Feb | C35: 45659 | D35: 1 | E35: 2500 | J35: 1000 | K35: =E35-I35-L35-M35-N35-J35+F35 -> 0 | N35: 1500 | O35: -500 | Q35: =N35+O35+P35 -> 1000
C36: 45691 | D36: 1 | E36: 2500 | I36: 1000 | K36: =E36-I36-L36-M36-N36-J36+F36 -> 0 | N36: 1500 | O36: -500 | Q36: =Q35+N36+O36+P36 -> 2000
C37: 45720 | D37: 1 | E37: 2000 | I37: 1000 | K37: =E37-I37-L37-M37-N37-J37+F37 -> 0 | N37: 1000 | O37: -500 | Q37: =Q36+N37+O37+P37 -> 2500
C38: 45753 | K38: =E38-I38-L38-M38-N38-J38+F38 -> 0 | Q38: =Q37+N38+O38+P38 -> 2500
C39: 45815 | D39: 1 | E39: 2000 | I39: 1000 | K39: =E39-I39-L39-M39-N39-J39+F39 -> 0 | N39: 1000 | O39: -500 | Q39: =Q38+N39+O39+P39 -> 3000
C40: 45846 | D40: 1 | E40: 2300 | I40: 1000 | K40: =E40-I40-L40-M40-N40-J40+F40 -> 0 | N40: 1300 | O40: -500 | Q40: =Q39+N40+O40+P40 -> 3800
C41: 45878 | D41: 1 | E41: 2500 | I41: 1000 | K41: =E41-I41-L41-M41-N41-J41+F41 -> 0 | N41: 1500 | O41: -500 | Q41: =Q40+N41+O41+P41 -> 4800
C42: 45911 | D42: 2 | E42: 4000 | I42: 1500 | K42: =E42-I42-L42-M42-N42-J42+F42 -> 0 | N42: 2500 | O42: -500 | Q42: =Q41+N42+O42+P42 -> 6800
C43: 45974 | K43: =E43-I43-L43-M43-N43-J43+F43 -> 0 | Q43: =Q42+N43+O43+P43 -> 6800
C44: 13-14 | D44: 1 | E44: 1800 | I44: 500 | K44: =E44-I44-L44-M44-N44-J44+F44 -> 0 | N44: 1300 | O44: -500 | Q44: =Q43+N44+O44+P44 -> 7600
C45: 14-15 | D45: 1 | E45: 3500 | I45: 1000 | K45: =E45-I45-L45-M45-N45-J45+F45 -> 0 | M45: =2500 -> 2500 | O45: -500 | Q45: =Q44+N45+O45+P45 -> 7100
E46: 1000 | H46: cancelled | I46: 1000 | K46: =E46-I46-L46-M46-N46-J46+F46 -> 0 | Q46: =Q45+N46+O46+P46 -> 7100
C47: 15-16 | D47: 1 | E47: 2500 | K47: =E47-I47-L47-M47-N47-J47+F47 -> 0 | N47: 2500 | O47: -500 | Q47: =Q46+N47+O47+P47 -> 9100
E48: 1000 | H48: cancelled | I48: 1000 | K48: =E48-I48-L48-M48-N48-J48+F48 -> 0 | Q48: =Q47+N48+O48+P48 -> 9100
C49: 16-17 | D49: 1 | E49: 2000 | I49: 500 | K49: =E49-I49-L49-M49-N49-J49+F49 -> 0 | N49: 1500 | O49: -500 | Q49: =Q48+N49+O49+P49 -> 10100
C50: 17-19 | D50: 2 | E50: 3500 | F50: 700 | I50: 1500 | K50: =E50-I50-L50-M50-N50-J50+F50 -> 0 | N50: 2700 | O50: -500 | Q50: =Q49+N50+O50+P50 -> 12300
C51: 19-20 | D51: 1 | E51: 2000 | I51: 1000 | K51: =E51-I51-L51-M51-N51-J51+F51 -> 0 | N51: 1000 | O51: -500 | Q51: =Q50+N51+O51+P51 -> 12800
C52: 20-21 | D52: 1 | E52: 2000 | I52: 500 | K52: =E52-I52-L52-M52-N52-J52+F52 -> 0 | N52: 1500 | O52: -500 | Q52: =Q51+N52+O52+P52 -> 13800
C53: 21-22 | D53: 1 | E53: 2100 | I53: 800 | K53: =E53-I53-L53-M53-N53-J53+F53 -> 0 | M53: 1300 | O53: -500 | Q53: =Q52+N53+O53+P53 -> 13300
C54: 22-23 | D54: 1 | E54: 2500 | I54: 1000 | K54: =E54-I54-L54-M54-N54-J54+F54 -> 0 | N54: 1500 | O54: -500 | Q54: =Q53+N54+O54+P54 -> 14300
C55: 23-24 | D55: 1 | E55: 1800 | I55: 500 | K55: =E55-I55-L55-M55-N55-J55+F55 -> 0 | N55: 1300 | O55: -500 | Q55: =Q54+N55+O55+P55 -> 15100
C56: 24-25 | D56: 1 | E56: 1800 | I56: 800 | K56: =E56-I56-L56-M56-N56-J56+F56 -> 0 | M56: 1000 | O56: -500 | Q56: =Q55+N56+O56+P56 -> 14600
C57: 25-24 | D57: 1 | E57: 2300 | G57: -700 | K57: =E57-I57-L57-M57-N57-J57+F57 -> 0 | N57: 2300 | O57: -500 | Q57: =Q56+N57+O57+P57 -> 16400
C58: 26-28 | D58: 2 | E58: =3800+500 -> 4300 | K58: =E58-I58-L58-M58-N58-J58+F58 -> 0 | M58: 1000 | N58: =2800+500 -> 3300 | O58: -500 | Q58: =Q57+N58+O58+P58 -> 19200
C59: 28-1 | D59: 1 | E59: 2300 | F59: 350 | I59: 1000 | K59: =E59-I59-L59-M59-N59-J59+F59 -> 0 | N59: 1650 | O59: -500 | Q59: =Q58+N59+O59+P59 -> 20350
K60: =E60-I60-L60-M60-N60-J60+F60 -> 0 | P60: -3209.08 | Q60: =Q59+N60+O60+P60 -> 17140.92 | R60: Meralco
K61: =E61-I61-L61-M61-N61-J61+F61 -> 0 | P61: -4909.98 | Q61: =Q60+N61+O61+P61 -> 12230.94 | R61: Association dues
P62: -12230.94 | Q62: =Q61+N62+O62+P62 -> 0
Q63: =Q61+N63+O63+P63 -> 12230.94 | R63: Remittance
B64: Feb | C64: Total | D64: =sum(D35:D60) -> 24 | E64: =sum(E35:E60) -> 54200 | G64: =sum(G35:G60) -> -700 | I64: =sum(I35:I60) -> 17600 | J64: =sum(J35:J60) -> 1000 | K64: =sum(K35:K60) -> 0 | L64: =sum(L35:L60) -> 0 | M64: =sum(M35:M60) -> 5800 | O64: =sum(O35:O60) -> -10500 | P64: =sum(P35:P60) -> -3209.08 | Q64: =Q62 -> 0
B65: Mar | C65: 45659 | D65: 1 | E65: 2299 | I65: 500 | K65: =E65-I65-L65-M65-N65-J65+F65 -> 0 | N65: 1799 | O65: -500 | Q65: =N65+O65+P65 -> 1299
E66: 500 | H66: cancelled | Q66: =Q65+N66+O66+P66 -> 1299
C67: 45691 | D67: 1 | E67: 2200 | I67: 1000 | K67: =E67-I67-L67-M67-N67-J67+F67 -> 0 | N67: 1200 | O67: -500 | Q67: =Q66+N67+O67+P67 -> 1999
C68: 45721 | K68: =E68-I68-L68-M68-N68-J68+F68 -> 0 | Q68: =Q67+N68+O68+P68 -> 1999
C69: 45783 | D69: 1 | E69: 2000 | F69: 350 | I69: 1200 | K69: =E69-I69-L69-M69-N69-J69+F69 -> 0 | N69: 1150 | O69: -500 | Q69: =Q68+N69+O69+P69 -> 2649
C70: 45815 | D70: 1 | E70: 2000 | I70: 1000 | K70: =E70-I70-L70-M70-N70-J70+F70 -> 0 | N70: 1000 | O70: -500 | Q70: =Q69+N70+O70+P70 -> 3149
C71: 45846 | D71: 1 | E71: 2000 | I71: 800 | K71: =E71-I71-L71-M71-N71-J71+F71 -> 0 | M71: 1200 | O71: -500 | Q71: =Q70+N71+O71+P71 -> 2649
C72: 45878 | D72: 1 | E72: 2500 | I72: 1000 | K72: =E72-I72-L72-M72-N72-J72+F72 -> 0 | N72: 1500 | O72: -500 | Q72: =Q71+N72+O72+P72 -> 3649
C73: 45910 | K73: =E73-I73-L73-M73-N73-J73+F73 -> 0 | Q73: =Q72+N73+O73+P73 -> 3649
C74: 45941 | D74: 1 | E74: 2000 | I74: 1000 | K74: =E74-I74-L74-M74-N74-J74+F74 -> 0 | N74: 1000 | O74: -500 | Q74: =Q73+N74+O74+P74 -> 4149
C75: 45975 | K75: =E75-I75-L75-M75-N75-J75+F75 -> 0 | Q75: =Q74+N75+O75+P75 -> 4149
C76: 14-16 | D76: 2 | E76: 4300 | I76: 1500 | K76: =E76-I76-L76-M76-N76-J76+F76 -> 0 | N76: 2800 | O76: -500 | Q76: =Q75+N76+O76+P76 -> 6449
C77: 16-18 | D77: 2 | E77: 3800 | I77: 1500 | K77: =E77-I77-L77-M77-N77-J77+F77 -> 0 | N77: 2300 | O77: -500 | Q77: =Q76+N77+O77+P77 -> 8249
C78: 18-19 | K78: =E78-I78-L78-M78-N78-J78+F78 -> 0 | Q78: =Q77+N78+O78+P78 -> 8249
C79: 19-20 | D79: 1 | E79: 1800 | I79: 500 | K79: =E79-I79-L79-M79-N79-J79+F79 -> 0 | N79: 1300 | O79: -500 | Q79: =Q78+N79+O79+P79 -> 9049
C80: 20-21 | K80: =E80-I80-L80-M80-N80-J80+F80 -> 0 | Q80: =Q79+N80+O80+P80 -> 9049
C81: 21-22 | D81: 1 | E81: 2000 | I81: 500 | K81: =E81-I81-L81-M81-N81-J81+F81 -> 0 | N81: 1500 | O81: -500 | Q81: =Q80+N81+O81+P81 -> 10049
C82: 22-23 | D82: 1 | E82: 2500 | I82: 1000 | K82: =E82-I82-L82-M82-N82-J82+F82 -> 0 | N82: 1500 | O82: -500 | Q82: =Q81+N82+O82+P82 -> 11049
C83: 23-24 | D83: 1 | E83: =2300 -> 2300 | I83: 1000 | K83: =E83-I83-L83-M83-N83-J83+F83 -> 0 | N83: 1300 | O83: -500 | Q83: =Q82+N83+O83+P83 -> 11849
C84: 24-25 | K84: =E84-I84-L84-M84-N84-J84+F84 -> 0 | Q84: =Q83+N84+O84+P84 -> 11849
C85: 25-26 | D85: 1 | E85: =2000+400 -> 2400 | I85: 1000 | K85: =E85-I85-L85-M85-N85-J85+F85 -> 0 | N85: 1400 | O85: -500 | Q85: =Q84+N85+O85+P85 -> 12749 | R85: 400 extend
C86: 26-28 | K86: =E86-I86-L86-M86-N86-J86+F86 -> 0 | Q86: =Q85+N86+O86+P86 -> 12749
C87: 28-29 | D87: 1 | E87: 2300 | I87: 1000 | K87: =E87-I87-L87-M87-N87-J87+F87 -> 0 | N87: 1300 | O87: -500 | Q87: =Q86+N87+O87+P87 -> 13549
C88: 29-30 | D88: 1 | E88: 2500 | I88: 1000 | K88: =E88-I88-L88-M88-N88-J88+F88 -> 0 | N88: 1500 | O88: -500 | Q88: =Q87+N88+O88+P88 -> 14549
C89: 30-31 | D89: 1 | E89: 2200 | I89: 1000 | K89: =E89-I89-L89-M89-N89-J89+F89 -> 0 | N89: 1200 | O89: -500 | Q89: =Q88+N89+O89+P89 -> 15249
K90: =E90-I90-L90-M90-N90-J90+F90 -> 0 | P90: -3766.42 | Q90: =Q89+N90+O90+P90 -> 11482.58 | R90: Meralco
K91: =E91-I91-L91-M91-N91-J91+F91 -> 0 | P91: -6260.74 | Q91: =Q90+N91+O91+P91 -> 5221.84 | R91: Association dues
P92: -1500 | Q92: =Q91+N92+O92+P92 -> 3721.84 | R92: Aircon cleaning
P93: -500 | Q93: =Q92+N93+O93+P93 -> 3221.84 | R93: Grease trap
P94: -3221.84 | Q94: =Q93+N94+O94+P94 -> 0 | R94: remittance
B95: Mar | C95: Total | D95: =sum(D65:D90) -> 19 | E95: =sum(E65:E94) -> 41599 | F95: =sum(F65:F94) -> 350 | G95: =sum(G65:G94) -> 0 | H95: =sum(H65:H94) -> 0 | I95: =sum(I65:I94) -> 16500 | J95: =sum(J65:J94) -> 0 | K95: =sum(K65:K94) -> 0 | L95: =sum(L65:L94) -> 0 | M95: =sum(M65:M94) -> 1200 | O95: =sum(O65:O94) -> -8500 | P95: =sum(P65:P94) -> -15249 | Q95: =Q94 -> 0
B96: Apr | C96: 45660 | D96: 2 | E96: 3500 | F96: 700 | I96: 1900 | K96: =E96-I96-L96-M96-N96-J96+F96 -> 0 | N96: 2300 | O96: -500 | Q96: =N96+O96+P96 -> 1800
C97: 45720 | K97: =E97-I97-L97-M97-N97-J97+F97 -> 0 | Q97: =Q96+N97+O97+P97 -> 1800
C98: 45752 | D98: 1 | E98: 2300 | F98: 350 | I98: 1200 | K98: =E98-I98-L98-M98-N98-J98+F98 -> 0 | M98: 1450 | O98: -500 | Q98: =Q97+N98+O98+P98 -> 1300
C99: 45783 | D99: 1 | E99: 2300 | K99: =E99-I99-L99-M99-N99-J99+F99 -> 0 | N99: 2300 | O99: -500 | Q99: =Q98+N99+O99+P99 -> 3100
E100: 1000 | H100: cancelled | I100: 1000 | Q100: =Q99+N100+O100+P100 -> 3100 | R100: cancelled
...

Sheet 1127
B1: 1127 BOOKING | L1: Payment | O1: 524 RECEIVABLE FROM ATE TESS
B2: Date | E2: Amount | F2: Parking | G2: Agent's Commission | H2: Remarks | I2: Reservation | K2: Balance | O2: Cleaning Fee | P2: Others | Q2: Receivable Balance | R2: Remarks
I3: BDO | J3: GCASH | L3: BDO | M3: GCASH | N3: Ate Tess
B4: DEC | C4: 45294 | K4: =E4-J4-L4-M4-N4-I4+F4 -> 0 | P4: 400 | Q4: =N4+O4+P4 -> 400 | R4: parking
C5: 45355 | D5: 1 | E5: 2000 | F5: 350 | J5: 1200 | K5: =E5-J5-L5-M5-N5-I5+F5 -> 0 | L5: 1150 | O5: -700 | Q5: =Q4+N5+O5+P5 -> -300
C6: 4-5 | D6: 1 | E6: 1707.2 | F6: 400 | H6: airbnb | K6: =E6-J6-L6-M6-N6-I6+F6-P6 -> 0 | L6: 1707.2 | O6: -700 | P6: 400 | Q6: =Q5+N6+O6+P6 -> -600 | R6: parking
C7: 45418 | D7: 1 | E7: 2600 | J7: 1000 | K7: =E7-J7-L7-M7-N7-I7+F7 -> 0 | N7: 1600 | O7: -700 | P7: 400 | Q7: =Q6+N7+O7+P7 -> 700 | R7: parking
C8: 6-7 | K8: =E8-J8-L8-M8-N8-I8+F8 -> 0 | Q8: =Q7+N8+O8+P8 -> 700
C9: 7-8 | D9: 1 | E9: 2700 | J9: 1000 | K9: =E9-J9-L9-M9-N9-I9+F9 -> 0 | M9: 1700 | O9: -700 | Q9: =Q8+N9+O9+P9 -> 0
C10: 45513 | D10: 1 | E10: 1707.2 | F10: 400 | H10: airbnb; p ate tess | K10: =E10-J10-L10-M10-N10-I10+F10-P10 -> 0 | L10: 1707.2 | O10: -700 | P10: 400 | Q10: =Q9+N10+O10+P10 -> -300
C11: 45545 | D11: 1 | E11: 2300 | F11: 400 | J11: 1000 | K11: =E11-J11-L11-M11-N11-I11+F11 -> 0 | M11: 1700 | O11: -700 | Q11: =Q10+N11+O11+P11 -> -1000
C12: 10-12 | D12: 2 | E12: 4100 | F12: 700 | I12: 1000 | J12: 500 | K12: =E12-J12-L12-M12-N12-I12+F12 -> 0 | L12: =2600+350 -> 2950 | N12: 350 | O12: -700 | Q12: =Q11+N12+O12+P12 -> -1350 | R12: parking
C13: 45639 | D13: 1 | E13: 2300 | J13: 2300 | K13: =E13-J13-L13-M13-N13-I13+F13 -> 0 | O13: -700 | P13: -150 | Q13: =Q12+N13+O13+P13 -> -2200
C14: 13-14 | D14: 1 | E14: 1637.51 | K14: =E14-J14-L14-M14-N14-I14+F14 -> 0 | L14: 1637.51 | O14: -700 | Q14: =Q13+N14+O14+P14 -> -2900
C15: 14-15 | D15: 1 | E15: 3200 | F15: 400 | J15: 1000 | K15: =E15-J15-L15-M15-N15-I15+F15 -> 0 | M15: 2600 | O15: -700 | Q15: =Q14+N15+O15+P15 -> -3600
C16: 15-16 | D16: 1 | E16: 2600 | F16: 400 | G16: -400 | J16: 1000 | K16: =E16-J16-L16-M16-N16-I16+F16 -> 0 | N16: 2000 | O16: -700 | Q16: =Q15+N16+O16+P16 -> -2300
C17: 16-17 | F17: 400 | K17: =E17-J17-L17-M17-N17-I17+F17 -> 0 | N17: 400 | Q17: =Q16+N17+O17+P17 -> -1900 | R17: parking
C18: 18-19 | D18: 1 | E18: 2300 | F18: 400 | J18: 1200 | K18: =E18-J18-L18-M18-N18-I18+F18 -> 0 | N18: 1500 | O18: -700 | Q18: =Q17+N18+O18+P18 -> -1100
C19: 19-20 | D19: 1 | E19: 2500 | G19: -400 | J19: 1000 | K19: =E19-J19-L19-M19-N19-I19+F19 -> 0 | N19: 1500 | O19: -700 | Q19: =Q18+N19+O19+P19 -> -300
C20: 20-21 | D20: 1 | E20: 2500 | J20: 500 | K20: =E20-J20-L20-M20-N20-I20+F20 -> 0 | N20: 2000 | O20: -700 | Q20: =Q19+N20+O20+P20 -> 1000
C21: 21-23 | D21: 2 | E21: =6700-450+50 -> 6300 | F21: =450 -> 450 | G21: -1000 | J21: =300+1600 -> 1900 | K21: =E21-J21-L21-M21-N21-I21+F21 -> 0 | N21: 4850 | O21: -700 | Q21: =Q20+N21+O21+P21 -> 5150
C22: 23-24 | D22: 1 | E22: 2500 | F22: 400 | J22: 1000 | K22: =E22-J22-L22-M22-N22-I22+F22-P22 -> 0 | N22: 1500 | O22: -700 | P22: 400 | Q22: =Q21+N22+O22+P22 -> 6350
C23: 24-26 | D23: 2 | E23: =4700*2 -> 9400 | F23: 1000 | J23: 2500 | K23: =E23-J23-L23-M23-N23-I23+F23 -> 0 | N23: 7900 | O23: -700 | P23: -1000 | Q23: =Q22+N23+O23+P23 -> 12550 | R23: violation
C24: 26-28 | D24: 2 | E24: 4500 | J24: 1500 | K24: =E24-J24-L24-M24-N24-I24+F24 -> 0 | N24: 3000 | O24: -700 | Q24: =Q23+N24+O24+P24 -> 14850
C25: 28-30 | D25: 2 | E25: 5700 | F25: 900 | J25: 1500 | K25: =E25-J25-L25-M25-N25-I25+F25 -> 0 | M25: 4200 | N25: 900 | O25: -700 | Q25: =Q24+N25+O25+P25 -> 15050
C26: 30-31 | K26: =E26-J26-L26-M26-N26-I26+F26 -> 0 | Q26: =Q25+N26+O26+P26 -> 15050
C27: 31-2 | D27: 2 | E27: 6700 | F27: 950 | J27: =2000+450 -> 2450 | K27: =E27-J27-L27-M27-N27-I27+F27 -> 0 | M27: 5200 | O27: -700 | P27: -5283.35 | Q27: =Q26+N27+O27+P27 -> 9066.65 | R27: Association dues
K28: =E28-J28-L28-M28-N28-I28+F28 -> 0 | P28: -4045 | Q28: =Q27+N28+O28+P28 -> 5021.65 | R28: Meralco | S28: 45662
P29: -50 | Q29: =Q28+N29+O29+P29 -> 4971.65 | R29: water
K30: =E30-J30-L30-M30-N30-I30+F30 -> 0 | P30: -500 | Q30: =Q29+N30+O30+P30 -> 4471.65 | R30: Grease trap
B31: DEC | C31: Total | D31: =sum(D4:D30) -> 26 | E31: =sum(E4:E30) -> 69251.91 | F31: =sum(F4:F30) -> 7550 | G31: =sum(G4:G30) -> -1800 | I31: =sum(I4:I30) -> 1000 | J31: =sum(J4:J30) -> 22550 | K31: =sum(K4:K30) -> 0 | L31: =sum(L4:L30) -> 9151.91 | M31: =sum(M4:M30) -> 15400 | N31: =sum(N4:N30) -> 27500 | O31: =sum(O4:O30) -> -14000 | P31: =sum(P4:P30) -> -9028.35 | Q31: =Q30 -> 4471.65
B32: JAN | C32: 45691 | D32: 1 | E32: 2300 | J32: 500 | K32: =E32-J32-L32-M32-N32-I32+F32 -> 0 | N32: 1800 | O32: -700 | Q32: =Q31+N32+O32+P32 -> 5571.65
C33: 45692 | E33: 1500 | H33: cancelled | J33: 1500 | K33: =E33-J33-L33-M33-N33-I33+F33 -> 0 | Q33: =Q32+N33+O33+P33 -> 5571.65 | R33: cancelled (2-4)
C34: 45720 | D34: 1 | E34: 2500 | J34: 1000 | K34: =E34-J34-L34-M34-N34-I34+F34 -> 0 | N34: 1500 | O34: -700 | Q34: =Q33+N34+O34+P34 -> 6371.65
C35: 45752 | D35: 1 | E35: 2800 | J35: 1000 | K35: =E35-J35-L35-M35-N35-I35+F35 -> 0 | N35: 1800 | O35: -700 | Q35: =Q34+N35+O35+P35 -> 7471.65
C36: 45785 | K36: =E36-J36-L36-M36-N36-I36+F36 -> 0 | Q36: =Q35+N36+O36+P36 -> 7471.65
C37: 45888 | D37: 11 | E37: 19000 | F37: =450+1950 -> 2400 | G37: -1000 | J37: =6000+2400 -> 8400 | K37: =E37-J37-L37-M37-N37-I37+F37-G37 -> 0 | N37: 14000 | O37: -700 | Q37: =Q36+N37+O37+P37 -> 20771.65
C38: 19-20 | K38: =E38-J38-L38-M38-N38-I38+F38 -> 0 | Q38: =Q37+N38+O38+P38 -> 20771.65
C39: 20-21 | D39: 1 | E39: 2000 | F39: 400 | J39: 500 | K39: =E39-J39-L39-M39-N39-I39+F39-P39 -> 0 | M39: 1500 | O39: -700 | P39: 400 | Q39: =Q38+N39+O39+P39 -> 20471.65 | R39: parking
C40: 21-22 | D40: 1 | E40: =1781.4 -> 1781.4 | F40: 400 | H40: airbnb | J40: 400 | K40: =E40-J40-L40-M40-N40-I40+F40-P40 -> 0 | L40: 1781.4 | O40: -700 | Q40: =Q39+N40+O40+P40 -> 19771.65
C41: 22-23 | K41: =E41-J41-L41-M41-N41-I41+F41-P41 -> 0 | Q41: =Q40+N41+O41+P41 -> 19771.65
C42: 23-25 | D42: 2 | E42: 3900 | F42: 800 | J42: 1800 | K42: =E42-J42-L42-M42-N42-I42+F42-P42 -> 0 | N42: 2900 | O42: -700 | Q42: =Q41+N42+O42+P42 -> 21971.65
C43: 25-26 | D43: 1 | E43: 2800 | F43: 400 | J43: 1000 | K43: =E43-J43-L43-M43-N43-I43+F43-P43 -> 0 | M43: 400 | N43: 1800 | O43: -700 | Q43: =Q42+N43+O43+P43 -> 23071.65
C44: 26-27 | F44: 400 | K44: =E44-J44-L44-M44-N44-I44+F44-P44 -> 0 | M44: 400 | Q44: =Q43+N44+O44+P44 -> 23071.65
C45: 27-29 | D45: 2 | E45: 4000 | F45: 300 | J45: 1000 | K45: =E45-J45-L45-M45-N45-I45+F45-P45 -> 0 | M45: 300 | N45: 3000 | O45: -700 | Q45: =Q44+N45+O45+P45 -> 25371.65
C46: 29-30 | D46: 1 | E46: 2500 | K46: =E46-J46-L46-M46-N46-I46+F46-P46 -> 0 | N46: 2500 | O46: -700 | Q46: =Q45+N46+O46+P46 -> 27171.65
C47: 30-1 | K47: =E47-J47-L47-M47-N47-I47+F47-P47 -> 0 | Q47: =Q46+N47+O47+P47 -> 27171.65
P48: -2465.91 | Q48: =Q47+N48+O48+P48 -> 24705.74 | R48: Meralco | S48: 45690
P49: -500 | Q49: =Q48+N49+O49+P49 -> 24205.74 | R49: Grease trap
P50: -50 | Q50: =Q49+N50+O50+P50 -> 24155.74 | R50: Water
K51: =E51-J51-L51-M51-N51-I51+F51 -> 0 | P51: -5481.7 | Q51: =Q50+N51+O51+P51 -> 18674.04 | R51: Association dues
P52: 0 | Q52: =Q51+N52+O52+P52 -> 18674.04 | R52: Remittance
B53: Jan | C53: Total | D53: =sum(D32:D52) -> 22 | E53: =sum(E32:E52) -> 45081.4 | F53: =sum(F32:F52) -> 5100 | G53: =sum(G32:G52) -> -1000 | H53: =sum(H32:H52) -> 0 | I53: =sum(I32:I52) -> 0 | J53: =sum(J32:J52) -> 17100 | K53: =sum(K32:K52) -> 0 | ... P53: =sum(P32:P52) -> -8097.61 | Q53: =Q52 -> 18674.04
B54: Feb | C54: 45659 | D54: 1 | E54: 2800 | F54: 800 | J54: 1000 | K54: =E54-J54-L54-M54-N54-I54+F54 -> 0 | N54: =1800+800 -> 2600 | O54: -700 | Q54: =Q53+N54+O54+P54 -> 20574.04 | R54: parking (800)
C55: 45692 | D55: 2 | E55: 5000 | J55: 2000 | K55: =E55-J55-L55-M55-N55-I55+F55 -> 0 | M55: 3000 | O55: -700 | Q55: =Q54+N55+O55+P55 -> 19874.04
C56: 45754 | K56: =E56-J56-L56-M56-N56-I56+F56 -> 0 | Q56: =Q55+N56+O56+P56 -> 19874.04
C57: 45846 | D57: 1 | E57: 2500 | J57: 1000 | K57: =E57-J57-L57-M57-N57-I57+F57 -> 0 | N57: 1500 | O57: -700 | Q57: =Q56+N57+O57+P57 -> 20674.04
C58: 45879 | D58: 2 | E58: =5300+500 -> 5800 | J58: 1500 | K58: =E58-J58-L58-M58-N58-I58+F58-G58 -> 0 | N58: 4300 | O58: -700 | Q58: =Q57+N58+O58+P58 -> 24274.04
C59: 45941 | K59: =E59-J59-L59-M59-N59-I59+F59-P59 -> 0 | Q59: =Q58+N59+O59+P59 -> 24274.04
C60: 45975 | D60: 3 | E60: 4209.8 | K60: =E60-J60-L60-M60-N60-I60+F60-P60 -> 0 | L60: 4209.8 | O60: -700 | Q60: =Q59+N60+O60+P60 -> 23574.04
C61: 14-16 | D61: 2 | E61: =5200+150 -> 5350 | F61: 800 | J61: 2000 | K61: =E61-J61-L61-M61-N61-I61+F61-P61 -> 0 | N61: =4000+150 -> 4150 | O61: -700 | Q61: =Q60+N61+O61+P61 -> 27024.04
C62: 16-17 | D62: 1 | E62: 2500 | J62: 1000 | K62: =E62-J62-L62-M62-N62-I62+F62-P62 -> 0 | M62: 1500 | O62: -700 | Q62: =Q61+N62+O62+P62 -> 26324.04
C63: 17-19 | D63: 2 | E63: 3800 | F63: 700 | J63: 1000 | K63: =E63-J63-L63-M63-N63-I63+F63-P63 -> 0 | M63: 2800 | N63: 700 | O63: -700 | Q63: =Q62+N63+O63+P63 -> 26324.04 | R63: parking (motor)
C64: 19-21 | K64: =E64-J64-L64-M64-N64-I64+F64-P64 -> 0 | Q64: =Q63+N64+O64+P64 -> 26324.04
C65: 21-22 | D65: 1 | E65: 2300 | J65: 1000 | K65: =E65-J65-L65-M65-N65-I65+F65-P65 -> 0 | N65: 1300 | O65: -700 | Q65: =Q64+N65+O65+P65 -> 26924.04
C66: 22-23 | D66: 1 | E66: 2800 | J66: 1000 | K66: =E66-J66-L66-M66-N66-I66+F66-P66 -> 0 | N66: 1800 | O66: -700 | Q66: =Q65+N66+O66+P66 -> 28024.04
C67: 23-25 | K67: =E67-J67-L67-M67-N67-I67+F67-P67 -> 0 | Q67: =Q66+N67+O67+P67 -> 28024.04
C68: 25-27 | D68: 2 | E68: 4100 | J68: 1500 | K68: =E68-J68-L68-M68-N68-I68+F68-P68 -> 0 | N68: 2600 | O68: -700 | Q68: =Q67+N68+O68+P68 -> 29924.04
C69: 27-28 | D69: 1 | E69: 2250 | J69: 1000 | K69: =E69-J69-L69-M69-N69-I69+F69-P69 -> 0 | N69: 1250 | O69: -700 | Q69: =Q68+N69+O69+P69 -> 30474.04
C70: 28-1 | D70: 1 | E70: 2500 | J70: 1000 | K70: =E70-J70-L70-M70-N70-I70+F70-P70 -> 0 | N70: 1500 | O70: -700 | Q70: =Q69+N70+O70+P70 -> 31274.04
P71: -2465.91 | Q71: =Q70+N71+O71+P71 -> 28808.13 | R71: Meralco | S71: 45706
P72: -500 | Q72: =Q71+N72+O72+P72 -> 28308.13 | R72: Grease trap
P73: -50 | Q73: =Q72+N73+O73+P73 -> 28258.13 | R73: Water
P74: -5257.98 | Q74: =Q73+N74+O74+P74 -> 23000.15 | R74: Association dues
P75: -23000.15 | Q75: =Q74+N75+O75+P75 -> 0 | R75: Remittance
B76: Feb | C76: Total | D76: =sum(D54:D75) -> 20 | E76: =sum(E54:E75) -> 45909.8 | F76: =sum(F54:F75) -> 2300 | G76: =sum(G54:G75) -> 0 | H76: =sum(H54:H75) -> 0 | I76: =sum(I54:I75) -> 0 | J76: =sum(J54:J75) -> 15000 | K76: =sum(K54:K75) -> 0 | ... P76: =sum(P54:P75) -> -31274.04 | Q76: =Q75 -> 0 | T76: 23
B77: Mar | C77: 45659 | D77: 1 | E77: 2800 | F77: 450 | J77: 1000 | K77: =E77-J77-L77-M77-N77-I77+F77-P77 -> 0 | N77: 2250 | O77: -700 | Q77: =Q76+N77+O77+P77 -> 1550 | T77: 23000.15
C78: 45692 | D78: 1 | E78: =1000+2500 -> 3500 | F78: 350 | J78: 1200 | K78: =E78-J78-L78-M78-N78-I78+F78-P78 -> 0 | M78: 2650 | O78: -700 | Q78: =Q77+N78+O78+P78 -> 850
C79: 45752 | Q79: =Q78+N79+O79+P79 -> 850
C80: 45784 | D80: 2 | E80: 4100 | J80: 1500 | K80: =E80-J80-L80-M80-N80-I80+F80-P80 -> 0 | M80: 2600 | O80: -700 | Q80: =Q79+N80+O80+P80 -> 150
C81: 45847 | D81: 2 | E81: 5100 | F81: 900 | J81: 1900 | M81: 4100 | O81: -700 | Q81: =Q80+N81+O81+P81 -> -550
C82: 45910 | K82: =E82-J82-L82-M82-N82-I82+F82-P82 -> 0 | Q82: =Q81+N82+O82+P82 -> -550
C83: 45941 | D83: 1 | E83: 2000 | J83: 1000 | K83: =E83-J83-L83-M83-N83-I83+F83-P83 -> 0 | N83: 1000 | O83: -700 | Q83: =Q82+N83+O83+P83 -> -250
C84: 45975 | K84: =E84-J84-L84-M84-N84-I84+F84-P84 -> 0 | Q84: =Q83+N84+O84+P84 -> -250
C85: 14-15 | D85: 1 | E85: 2200 | J85: 500 | K85: =E85-J85-L85-M85-N85-I85+F85-P85 -> 0 | N85: 1700 | O85: -700 | Q85: =Q84+N85+O85+P85 -> 750
C86: 15-16 | D86: 1 | E86: 2800 | J86: 1000 | K86: =E86-J86-L86-M86-N86-I86+F86-P86 -> 0 | M86: 1800 | O86: -700 | Q86: =Q85+N86+O86+P86 -> 50
C87: 16-28 | D87: 10 | E87: =4400-800+21100 -> 24700 | F87: =800+4000 -> 4800 | J87: 7500 | K87: =E87-J87-L87-M87-N87-I87+F87-P87 -> 0 | M87: =13800+4400 -> 18200 | N87: 3800 | O87: -700 | Q87: =Q86+N87+O87+P87 -> 3150 | R87: Mary andersen
C88: 28-29 | D88: 1 | E88: 2500 | J88: 1000 | K88: =E88-J88-L88-M88-N88-I88+F88-P88 -> 0 | N88: 1500 | O88: -700 | Q88: =Q87+N88+O88+P88 -> 3950
C89: 29-30 | D89: 1 | E89: 3050 | J89: 1000 | K89: =E89-J89-L89-M89-N89-I89+F89-P89 -> 0 | M89: 1050 | N89: 1000 | O89: -700 | Q89: =Q88+N89+O89+P89 -> 4250
C90: 30-31 | D90: 1 | E90: 2000 | J90: 1000 | K90: =E90-J90-L90-M90-N90-I90+F90-P90 -> 0 | M90: 1000 | O90: -700 | Q90: =Q89+N90+O90+P90 -> 3550
C91: 31-1 | D91: 1 | E91: 1800 | K91: =E91-J91-L91-M91-N91-I91+F91-P91 -> 0 | N91: 1800 | O91: -700 | Q91: =Q90+N91+O91+P91 -> 4650
P92: -1992.87 | Q92: =Q91+N92+O92+P92 -> 2657.13 | R92: Meralco MAR | S92: 45733
P93: -1892.75 | Q93: =Q92+N93+O93+P93 -> 764.38 | R93: Meralco FEB | S93: 45741
P94: -6442.18 | Q94: =Q93+N94+O94+P94 -> -5677.8 | R94: Association dues
P95: -500 | Q95: =Q94+N95+O95+P95 -> -6177.8 | R95: grease trap
B96: Mar | C96: Total | D96: =sum(D77:D95) -> 23 | E96: =sum(E77:E95) -> 56550 | F96: =sum(F77:F95) -> 6500 | G96: =sum(G77:G95) -> 0 | H96: =sum(H77:H95) -> 0 | I96: =sum(I77:I95) -> 0 | J96: =sum(J77:J95) -> 18600 | K96: =sum(K77:K95) -> 0 | ... P96: =sum(P77:P95) -> -10827.8 | Q96: =Q95 -> -6177.8
B97: April | C97: 45662 | K97: =E97-J97-L97-M97-N97-I97+F97-P97 -> 0 | Q97: =Q96+N97+O97+P97 -> -6177.8
B98: April | C98: 45783 | D98: 1 | E98: 2800 | F98: 400 | J98: 1000 | K98: =E98-J98-L98-M98-N98-I98+F98-P98 -> -400 | L98: 2200 | N98: 400 | O98: -700 | Q98: =Q97+N98+O98+P98 -> -6477.8 | R98: parking
C99: 45815 | D99: 1 | E99: 2000 | F99: 750 | J99: 500 | K99: =E99-J99-L99-M99-N99-I99+F99-P99 -> 0 | N99: 2250 | O99: -700 | Q99: =Q98+N99+O99+P99 -> -4927.8 | R99: 750 parking
C100: 45850 | F100: 300 | K100: =E100-J100-L100-M100-N100-I100+F100-P100 -> 0 | N100: 300 | Q100: =Q99+N100+O100+P100 -> -4627.8 | R100: parking
...

Sheet 1228
B1: 1228 BOOKING | L1: Full payment | P1: 1228 RECEIVABLE FROM ATE TESS
B2: Date | E2: Amount | F2: Parking | G2: Agent's Commissions | H2: Remarks | I2: Reservation | K2: Balance | O2: Cleaning Fee | P2: Others | Q2: Receivable Balance | R2: Remarks
I3: BDO | J3: Gcash | L3: BDO | M3: GCASH | N3: ATE TESS
B4: DEC | C4: 45293 | D4: 1 | E4: 1804.2 | H4: airbnb | K4: =E4-J4-L4-M4-N4-I4 -> 0 | L4: 1804.2 | O4: -700 | Q4: =N4+O4+P4 -> -700
C5: 45326 | K5: =E5-J5-L5-M5-N5-I5 -> 0 | Q5: =Q4+N5+O5+P5 -> -700
C6: 45387 | D6: 1 | E6: 2700 | J6: 1000 | K6: =E6-J6-L6-M6-N6-I6 -> 0 | N6: 1700 | O6: -700 | Q6: =Q5+N6+O6+P6 -> 300
C7: 45418 | D7: 1 | E7: 1788.68 | H7: Airbnb | K7: =E8-J8-L8-M8-N8-I8 -> 0 | L7: 1788.68 | O7: -700 | Q7: =Q6+N7+O7+P7 -> -400
C8: 45450 | D8: 1 | E8: 2000 | J8: 500 | K8: =E8-J8-L8-M8-N8-I8 -> 0 | M8: 1500 | O8: -700 | Q8: =Q7+N8+O8+P8 -> -1100
C9: 7-8 | D9: 1 | E9: 3000 | J9: 1000 | K9: =E9-J9-L9-M9-N9-I9 -> 0 | N9: 2000 | O9: -700 | Q9: =Q8+N9+O9+P9 -> 200
C10: 45513 | D10: 1 | E10: 2800 | J10: 1000 | K10: =E10-J10-L10-M10-N10-I10 -> 0 | L10: 1800 | O10: -700 | Q10: =Q9+N10+O10+P10 -> -500
C11: 45546 | D11: 2 | E11: 4300 | J11: 1500 | K11: =E11-J11-L11-M11-N11-I11 -> 0 | M11: 2800 | O11: -700 | Q11: =Q10+N11+O11+P11 -> -1200
C12: 45610 | K12: =E12-J12-L12-M12-N12-I12 -> 0 | Q12: =Q11+N12+O12+P12 -> -1200
C13: 14-15 | D13: 1 | E13: 2700 | J13: 1000 | K13: =E13-J13-L13-M13-N13-I13 -> 0 | N13: 1700 | O13: -700 | Q13: =Q12+N13+O13+P13 -> -200
C14: 15-18 | Q14: =Q13+N14+O14+P14 -> -200
C15: 18-19 | D15: 1 | E15: 2500 | J15: 1000 | K15: =E15-J15-L15-M15-N15-I15 -> 0 | M15: 1500 | O15: -700 | Q15: =Q14+N15+O15+P15 -> -900
C16: 19-20 | D16: 1 | E16: 2500 | J16: 1000 | K16: =E16-J16-L16-M16-N16-I16 -> 0 | N16: 1500 | O16: -700 | Q16: =Q15+N16+O16+P16 -> -100
C17: 20-21 | D17: 1 | E17: 2300 | J17: 1000 | K17: =E17-J17-L17-M17-N17-I17 -> 0 | N17: 1300 | O17: -700 | Q17: =Q16+N17+O17+P17 -> 500
C18: 21-22 | D18: 1 | E18: 3200 | J18: 1000 | K18: =E18-J18-L18-M18-N18-I18 -> 0 | N18: 2200 | O18: -700 | Q18: =Q17+N18+O18+P18 -> 2000
C19: 22-23 | D19: 1 | E19: 2300 | J19: 500 | K19: =E19-J19-L19-M19-N19-I19 -> 0 | N19: 1800 | O19: -700 | Q19: =Q18+N19+O19+P19 -> 3100
C20: 23-24 | D20: 1 | E20: 2500 | J20: 1000 | K20: =E20-J20-L20-M20-N20-I20 -> 0 | N20: 1500 | O20: -700 | Q20: =Q19+N20+O20+P20 -> 3900
C21: 24-26 | D21: 2 | E21: 7700 | J21: 1500 | K21: =E21-J21-L21-M21-N21-I21 -> 0 | M21: 1300 | N21: 4900 | O21: -700 | P21: -1000 | Q21: =Q20+N21+O21+P21 -> 7100
C22: 26-27 | D22: 1 | E22: 2100 | J22: 1000 | K22: =E22-J22-L22-M22-N22-I22 -> 0 | N22: 1100 | O22: -700 | Q22: =Q21+N22+O22+P22 -> 7500
C23: 27-28 | D23: 1 | E23: 3000 | J23: 1000 | K23: =E23-J23-L23-M23-N23-I23 -> 0 | N23: 2000 | O23: -700 | Q23: =Q22+N23+O23+P23 -> 8800
C24: 28-29 | D24: 1 | E24: 3000 | J24: 1000 | K24: =E24-J24-L24-M24-N24-I24 -> 0 | N24: 2000 | O24: -700 | Q24: =Q23+N24+O24+P24 -> 10100
C25: 29-30 | D25: 1 | E25: 3700 | J25: 1000 | K25: =E25-J25-L25-M25-N25-I25 -> 0 | N25: 2700 | O25: -700 | Q25: =Q24+N25+O25+P25 -> 12100
C26: 30-1 | D26: 2 | E26: 5700 | J26: 1500 | K26: =E26-J26-L26-M26-N26-I26 -> 0 | L26: 4200 | O26: -700 | Q26: =Q25+N26+O26+P26 -> 11400
K27: =E27-J27-L27-M27-N27-I27 -> 0 | P27: -500 | Q27: =Q26+N27+O27+P27 -> 10900 | R27: grease trap
K28: =E28-J28-L28-M28-N28-I28 -> 0 | P28: -5081.29 | Q28: =Q27+N28+O28+P28 -> 5818.71 | R28: Association Dues
B29: DEC | C29: TOTAL | D29: =SUM(D4:D28) -> 23 | E29: =SUM(E4:E28) -> 61592.88 | G29: =SUM(G4:G28) -> 0 | H29: =SUM(H4:H28) -> 0 | I29: =SUM(I4:I28) -> 0 | J29: =SUM(J4:J28) -> 18500 | K29: =SUM(K4:K28) -> 0 | L29: =SUM(L4:L28) -> 9592.88 | M29: =SUM(M4:M28) -> 7100 | N29: =SUM(N4:N28) -> 26400 | ... P29: =SUM(P4:P28) -> -6581.29 | Q29: =Q28 -> 5818.71
B30: Jan | C30: 45659 | D30: 1 | E30: 2800 | J30: 1000 | K30: =E30-J30-L30-M30-N30-I30 -> 0 | N30: 1800 | O30: -700 | Q30: =Q29+N30+O30+P30 -> 6918.71
C31: 45691 | D31: 1 | E31: 2300 | J31: 1000 | K31: =E31-J31-L31-M31-N31-I31 -> 0 | N31: 1300 | O31: -700 | Q31: =Q30+N31+O31+P31 -> 7518.71
C32: 3-4 | D32: 1 | E32: 2750 | J32: 1000 | K32: =E32-J32-L32-M32-N32-I32 -> 0 | L32: 1750 | O32: -700 | Q32: =Q31+N32+O32+P32 -> 6818.71
C33: 45752 | D33: 1 | E33: 2800 | J33: 1000 | K33: =E33-J33-L33-M33-N33-I33 -> 0 | N33: 1800 | O33: -700 | Q33: =Q32+N33+O33+P33 -> 7918.71
C34: 5-6 | D34: 1 | E34: 2200 | G34: 400 | J34: 1000 | K34: =E34-J34-L34-M34-N34-I34 -> 0 | N34: 1200 | O34: -700 | Q34: =Q33+N34+O34+P34 -> 8418.71
C35: 45815 | D35: 1 | E35: 2300 | J35: 500 | K35: =E35-J35-L35-M35-N35-I35 -> 0 | N35: 1800 | O35: -700 | Q35: =Q34+N35+O35+P35 -> 9518.71
C36: 45848 | K36: =E36-J36-L36-M36-N36-I36 -> 0 | Q36: =Q35+N36+O36+P36 -> 9518.71
C37: 45942 | D37: 2 | E37: 5300 | J37: 1500 | K37: =E37-J37-L37-M37-N37-I37 -> 0 | M37: 3800 | O37: -700 | Q37: =Q36+N37+O37+P37 -> 8818.71
C38: 46004 | D38: 1 | E38: =2800+400 -> 3200 | J38: 1000 | K38: =E38-J38-L38-M38-N38-I38 -> 0 | M38: 2200 | O38: -700 | Q38: =Q37+N38+O38+P38 -> 8118.71
C39: 14-15 | K39: =E39-J39-L39-M39-N39-I39 -> 0 | Q39: =Q38+N39+O39+P39 -> 8118.71
C40: 15-16 | D40: 1 | E40: 2300 | J40: 1000 | K40: =E40-J40-L40-M40-N40-I40 -> 0 | N40: 1300 | O40: -700 | Q40: =Q39+N40+O40+P40 -> 8718.71
C41: 16-17 | D41: 1 | E41: 2000 | J41: 1000 | K41: =E41-J41-L41-M41-N41-I41 -> 0 | N41: 1000 | O41: -700 | Q41: =Q40+N41+O41+P41 -> 9018.71
C42: 17-18 | D42: 1 | E42: 2000 | J42: 1000 | K42: =E42-J42-L42-M42-N42-I42 -> 0 | N42: 1000 | O42: -700 | Q42: =Q41+N42+O42+P42 -> 9318.71
C43: 18-19 | D43: 1 | E43: 2800 | J43: 1000 | K43: =E43-J43-L43-M43-N43-I43 -> 0 | M43: 1800 | O43: -700 | Q43: =Q42+N43+O43+P43 -> 8618.71
C44: 19-20 | D44: 1 | E44: 1969.1 | K44: =E44-J44-L44-M44-N44-I44 -> 0 | L44: 1969.1 | O44: -700 | Q44: =Q43+N44+O44+P44 -> 7918.71
C45: 20-21 | D45: 1 | E45: 2000 | J45: 500 | K45: =E45-J45-L45-M45-N45-I45 -> 0 | N45: 1500 | O45: -700 | Q45: =Q44+N45+O45+P45 -> 8718.71
C46: 20-22 | E46: 500 | H46: CANCELLED | J46: 500 | K46: =E46-J46-L46-M46-N46-I46 -> 0 | Q46: =Q45+N46+O46+P46 -> 8718.71
C47: 22-23 | D47: 1 | E47: 2500 | K47: =E47-J47-L47-M47-N47-I47 -> 0 | N47: 2500 | O47: -700 | P47: -500 | Q47: =Q46+N47+O47+P47 -> 10018.71 | R47: 500 VIOLATION
C48: 23-24 | K48: =E48-J48-L48-M48-N48-I48 -> 0 | Q48: =Q47+N48+O48+P48 -> 10018.71
C49: 24-25 | D49: 1 | E49: 2200 | J49: 1000 | K49: =E49-J49-L49-M49-N49-I49 -> 0 | M49: 1200 | O49: -700 | Q49: =Q48+N49+O49+P49 -> 9318.71
C50: 25-26 | E50: 1000 | H50: CACELLED | J50: 1000 | K50: =E50-J50-L50-M50-N50-I50 -> 0 | Q50: =Q49+N50+O50+P50 -> 9318.71 | R50: Cancelled
C51: 25-27 | D51: 2 | E51: 5000 | J51: 1500 | K51: =E51-J51-L51-M51-N51-I51 -> 0 | M51: 3500 | O51: -700 | Q51: =Q50+N51+O51+P51 -> 8618.71
C52: 27-28 | D52: 1 | E52: 2500 | J52: 1000 | K52: =E52-J52-L52-M52-N52-I52 -> 0 | N52: 1500 | O52: -700 | Q52: =Q51+N52+O52+P52 -> 9418.71
C53: 28-30 | D53: 2 | E53: 6000 | J53: 1500 | K53: =E53-J53-L53-M53-N53-I53 -> 0 | N53: 4500 | O53: -700 | P53: -1000 | Q53: =Q52+N53+O53+P53 -> 12218.71 | R53: violation
C54: 30-31 | K54: =E54-J54-L54-M54-N54-I54 -> 0 | Q54: =Q53+N54+O54+P54 -> 12218.71
C55: 31-1 | D55: 1 | E55: 2500 | J55: 500 | K55: =E55-J55-L55-M55-N55-I55 -> 0 | N55: 2000 | O55: -700 | Q55: =Q54+N55+O55+P55 -> 13518.71
K56: =E56-J56-L56-M56-N56-I56 -> 0 | P56: -500 | Q56: =Q55+N56+O56+P56 -> 13018.71 | R56: grease trap
K57: =E57-J57-L57-M57-N57-I57 -> 0 | P57: -5813.68 | Q57: =Q56+N57+O57+P57 -> 7205.03 | R57: Association Dues
K58: =E58-J58-L58-M58-N58-I58 -> 0 | Q58: =Q57+N58+O58+P58 -> 7205.03 | R58: Remittance
B59: JAN | C59: TOTAL | D59: =sum(D30:D58) -> 23 | E59: =sum(E30:E58) -> 58919.1 | G59: =sum(G30:G58) -> 400 | H59: =sum(H30:H58) -> 0 | I59: =sum(I30:I58) -> 0 | J59: =sum(J30:J58) -> 19500 | K59: =sum(K30:K58) -> 0 | L59: =sum(L30:L58) -> 3719.1 | M59: =sum(M30:M58) -> 12500 | N59: =sum(N30:N58) -> 23200 | ... P59: =sum(P30:P58) -> -7813.68 | Q59: =Q58 -> 7205.03
B60: FEB | C60: 45659 | D60: 1 | E60: 2800 | I60: 1000 | K60: =E60-J60-L60-M60-N60-I60 -> 0 | N60: 1800 | O60: -700 | Q60: =Q59+N60+O60+P60 -> 8305.03
C61: 45693 | D61: 3 | E61: 4937.3 | H61: Airbnb | K61: =E61-J61-L61-M61-N61-I61 -> 0 | L61: 4937.3 | O61: -700 | Q61: =Q60+N61+O61+P61 -> 7605.03
C62: 45783 | K62: =E62-J62-L62-M62-N62-I62 -> 0 | Q62: =Q61+N62+O62+P62 -> 7605.03
C63: 45815 | D63: 1 | E63: 1749.1 | K63: =E63-J63-L63-M63-N63-I63 -> 0 | L63: 1749.1 | O63: -700 | Q63: =Q62+N63+O63+P63 -> 6905.03
C64: 45846 | K64: =E64-J64-L64-M64-N64-I64 -> 0 | O64: -700 | Q64: =Q63+N64+O64+P64 -> 6205.03
C65: 45878 | D65: 1 | E65: =4500-500 -> 4000 | J65: 1000 | K65: =E65-J65-L65-M65-N65-I65 -> 0 | M65: 3500 | N65: -500 | O65: -700 | Q65: =Q64+N65+O65+P65 -> 5005.03 | R65: violation
C66: 45910 | D66: 1 | E66: =2500+450 -> 2950 | J66: 1250 | K66: =E66-J66-L66-M66-N66-I66 -> 0 | N66: 1700 | O66: -700 | Q66: =Q65+N66+O66+P66 -> 6005.03
C67: 45941 | D67: 1 | E67: 1800 | J67: 500 | K67: =E67-J67-L67-M67-N67-I67 -> 0 | M67: 1300 | O67: -700 | Q67: =Q66+N67+O67+P67 -> 5305.03
C68: 45974 | K68: =E68-J68-L68-M68-N68-I68 -> 0 | Q68: =Q67+N68+O68+P68 -> 5305.03
C69: 13-14 | D69: 1 | E69: 2300 | J69: 1000 | K69: =E69-J69-L69-M69-N69-I69 -> 0 | N69: 1300 | O69: -700 | Q69: =Q68+N69+O69+P69 -> 5905.03
C70: 14-15 | D70: 1 | E70: 2800 | J70: 1000 | K70: =E70-J70-L70-M70-N70-I70 -> 0 | M70: 1800 | O70: -700 | Q70: =Q69+N70+O70+P70 -> 5205.03
C71: 15-16 | D71: 1 | E71: 2800 | J71: 1000 | K71: =E71-J71-L71-M71-N71-I71 -> 0 | M71: 1800 | O71: -700 | Q71: =Q70+N71+O71+P71 -> 4505.03
C72: 16-17 | D72: 1 | E72: 2439.55 | K72: =E72-J72-L72-M72-N72-I72 -> 0 | L72: 2439.55 | O72: 700 | Q72: =Q71+N72+O72+P72 -> 5205.03
C73: 17-18 | K73: =E73-J73-L73-M73-N73-I73 -> 0 | Q73: =Q72+N73+O73+P73 -> 5205.03
C74: 18-19 | D74: 1 | E74: 1886.65 | K74: =E74-J74-L74-M74-N74-I74 -> 0 | L74: 1886.65 | O74: -700 | Q74: =Q73+N74+O74+P74 -> 4505.03
C75: 19-21 | K75: =E75-J75-L75-M75-N75-I75 -> 0 | Q75: =Q74+N75+O75+P75 -> 4505.03
C76: 21-23 | D76: 2 | E76: 5100 | J76: 1000 | K76: =E76-J76-L76-M76-N76-I76 -> 0 | M76: 4100 | O76: -700 | Q76: =Q75+N76+O76+P76 -> 3805.03
C77: 23-24 | D77: 1 | E77: 3500 | J77: 1000 | K77: =E77-J77-L77-M77-N77-I77 -> 0 | N77: 2500 | O77: -700 | Q77: =Q76+N77+O77+P77 -> 5605.03
C78: 24-26 | K78: =E78-J78-L78-M78-N78-I78 -> 0 | Q78: =Q77+N78+O78+P78 -> 5605.03
C79: 26-27 | D79: 1 | E79: 2550 | J79: 1000 | K79: =E79-J79-L79-M79-N79-I79 -> 0 | N79: 1550 | O79: -700 | Q79: =Q78+N79+O79+P79 -> 6455.03
C80: 27-28 | Q80: =Q79+N80+O80+P80 -> 6455.03
C81: 28-2 | D81: 2 | E81: 6800 | J81: 1500 | K81: =E81-J81-L81-M81-N81-I81 -> 0 | M81: 5300 | O81: -700 | Q81: =Q80+N81+O81+P81 -> 5755.03
K82: =E82-J82-L82-M82-N82-I82 -> 0 | P82: -500 | Q82: =Q81+N82+O82+P82 -> 5255.03 | R82: grease trap
K83: =E83-J83-L83-M83-N83-I83 -> 0 | P83: -4977 | Q83: =Q82+N83+O83+P83 -> 278.03 | R83: Association Dues
K84: =E84-J84-L84-M84-N84-I84 -> 0 | P84: -278.03 | Q84: =Q83+N84+O84+P84 -> 0
B85: FEB | C85: TOTAL | D85: =sum(D60:D84) -> 19 | E85: =sum(E60:E84) -> 48412.6 | G85: =sum(G60:G84) -> 0 | H85: =sum(H60:H84) -> 0 | I85: =sum(I60:I84) -> 1000 | J85: =sum(J60:J84) -> 10250 | K85: =sum(K60:K84) -> 0 | L85: =sum(L60:L84) -> 11012.6 | M85: =sum(M60:M84) -> 17800 | N85: =sum(N60:N84) -> 8350 | ... P85: =sum(P60:P84) -> -5755.03 | Q85: =Q84 -> 0
B86: MAR | C86: 45692 | K86: =E86-J86-L86-M86-N86-I86+F86 -> 0 | Q86: =Q85+N86+O86+P86 -> 0
B87: MAR | C87: 45753 | D87: 2 | E87: 4000 | J87: 1000 | K87: =E87-J87-L87-M87-N87-I87+F87 -> 0 | N87: 3000 | O87: -700 | Q87: =Q86+N87+O87+P87 -> 2300
C88: 45815 | K88: =E88-J88-L88-M88-N88-I88+F88 -> 0 | Q88: =Q87+N88+O88+P88 -> 2300
C89: 45846 | D89: 1 | E89: 2300 | J89: 1000 | K89: =E89-J89-L89-M89-N89-I89+F89 -> 0 | M89: 1300 | O89: -700 | Q89: =Q88+N89+O89+P89 -> 1600
C90: 45878 | D90: 1 | E90: 2800 | J90: 1000 | K90: =E90-J90-L90-M90-N90-I90+F90 -> 0 | N90: 1800 | O90: -700 | Q90: =Q89+N90+O90+P90 -> 2700
C91: 45911 | K91: =E91-J91-L91-M91-N91-I91+F91 -> 0 | Q91: =Q90+N91+O91+P91 -> 2700
C92: 45978 | D92: 6 | E92: =12100+600 -> 12700 | H92: extend | J92: 3500 | K92: =E92-J92-L92-M92-N92-I92+F92 -> 0 | M92: 9200 | O92: -700 | Q92: =Q91+N92+O92+P92 -> 2000
C93: 17-22 | K93: =E93-J93-L93-M93-N93-I93+F93 -> 0 | Q93: =Q92+N93+O93+P93 -> 2000
C94: 22-24 | D94: 2 | E94: 4400 | J94: 1000 | K94: =E94-J94-L94-M94-N94-I94+F94 -> 0 | N94: 3400 | O94: -700 | Q94: =Q93+N94+O94+P94 -> 4700
C95: 24-25 | K95: =E95-J95-L95-M95-N95-I95+F95 -> 0 | Q95: =Q94+N95+O95+P95 -> 4700
C96: 25-26 | D96: 1 | E96: 2300 | J96: 1000 | K96: =E96-J96-L96-M96-N96-I96+F96 -> 0 | N96: 1300 | O96: -700 | Q96: =Q95+N96+O96+P96 -> 5300
C97: 26-27 | K97: =E97-J97-L97-M97-N97-I97+F97 -> 0 | Q97: =Q96+N97+O97+P97 -> 5300
C98: 27-28 | D98: 1 | E98: 4100 | J98: 1000 | K98: =E98-J98-L98-M98-N98-I98+F98 -> 0 | N98: 3100 | O98: -700 | P98: -500 | Q98: =Q97+N98+O98+P98 -> 7200 | R98: 500 violation
C99: 28-30 | D99: 2 | E99: 6000 | F99: 700 | J99: 1900 | K99: =E99-J99-L99-M99-N99-I99+F99 -> 0 | N99: 4800 | O99: -700 | Q99: =Q98+N99+O99+P99 -> 11300
C100: 30-2 | D100: 4 | E100: 4937.3 | K100: =E100-J100-L100-M100-N100-I100+F100 -> 0 | L100: 4937.3 | O100: -700 | Q100: =Q99+N100+O100+P100 -> 10600
...

Sheet 1230
B1: 1230 BOOKING | L1: Payment | O1: 1230 RECEIVABLE FROM ATE TESS
B2: Date | E2: Amount | F2: Parking | G2: Agent's Commission | H2: Remarks | I2: Reservation | K2: Balance | O2: Cleaning Fee | P2: Others | Q2: Receivable Balance | R2: Remarks
I3: BDO | J3: Gcash | L3: BDO | M3: GCASH | N3: Ate Tess
B4: DEC | C4: 45293 | D4: 1 | E4: 1804.2 | F4: 400 | K4: =E4-J4-L4-M4-N4-I4+F4 -> 0 | L4: 1804.2 | N4: 400 | O4: -700 | Q4: =N4+O4+P4 -> -300
C5: 45325 | K5: =E5-J5-L5-M5-N5-I5+F5 -> 0 | Q5: =Q4+N5+O5+P5 -> -300
C6: 3-4 | D6: 1 | E6: 2260.1 | H6: airbnb | K6: =E6-J6-L6-M6-N6-I6+F6 -> 0 | L6: 2260.1 | O6: -700 | Q6: =Q5+N6+O6+P6 -> -1000
C7: 4-6 | D7: 2 | E7: 4100 | J7: 1000 | K7: =E7-J7-L7-M7-N7-I7+F7 -> 0 | N7: 3100 | O7: -700 | Q7: =Q6+N7+O7+P7 -> 1400
C8: 45450 | D8: 1 | E8: 2500 | J8: 1000 | K8: =E8-J8-L8-M8-N8-I8+F8 -> 0 | N8: 1500 | O8: -700 | Q8: =Q7+N8+O8+P8 -> 2200
C9: 45482 | E9: 1500 | H9: cancelled | J9: 1500 | K9: =E9-J9-L9-M9-N9-I9+F9 -> 0 | Q9: =Q8+N9+O9+P9 -> 2200
C10: 45481 | D10: 1 | E10: 2800 | K10: =E10-J10-L10-M10-N10-I10+F10 -> 0 | N10: 2800 | O10: -700 | Q10: =Q9+N10+O10+P10 -> 4300
C11: 45513 | D11: 1 | E11: 2500 | H11: 400 to ate tess | K11: =E11-J11-L11-M11-N11-I11+F11 -> 0 | N11: 2500 | O11: -700 | P11: -400 | Q11: =Q10+N11+O11+P11 -> 5700 | R11: parking ate tess
C12: 9-10 | D12: 1 | E12: =2300+200 -> 2500 | J12: 1000 | K12: =E12-J12-L12-M12-N12-I12+F12 -> 0 | M12: 200 | N12: 1300 | O12: -700 | Q12: =Q11+N12+O12+P12 -> 6300
C13: 10-11 | K13: =E13-J13-L13-M13-N13-I13+F13 -> 0 | Q13: =Q12+N13+O13+P13 -> 6300
C14: 11-13 | D14: 2 | E14: 4100 | I14: 1500 | K14: =E14-J14-L14-M14-N14-I14+F14 -> 0 | N14: 2600 | O14: -700 | Q14: =Q13+N14+O14+P14 -> 8200
C15: 13-14 | E15: 500 | H15: cancelled | K15: =E15-J15-L15-M15-N15-I15+F15 -> 0 | M15: 500 | Q15: =Q14+N15+O15+P15 -> 8200
C16: 14-15 | D16: 1 | E16: 3000 | J16: 1000 | K16: =E16-J16-L16-M16-N16-I16+F16 -> 0 | N16: 2000 | O16: -700 | Q16: =Q15+N16+O16+P16 -> 9500
C17: 15-16 | D17: 1 | E17: 2800 | J17: 1000 | K17: =E17-J17-L17-M17-N17-I17+F17 -> 0 | N17: 1800 | O17: -700 | Q17: =Q16+N17+O17+P17 -> 10600
C18: 16-18 | D18: 2 | E18: 3500 | J18: 1500 | K18: =E18-J18-L18-M18-N18-I18+F18 -> 0 | M18: 2000 | O18: -700 | Q18: =Q17+N18+O18+P18 -> 9900
C19: 18-19 | D19: 1 | E19: 1993.83 | K19: =E19-J19-L19-M19-N19-I19+F19 -> 0 | L19: 1993.83 | O19: -700 | Q19: =Q18+N19+O19+P19 -> 9200
C20: 19-20 | D20: 1 | E20: 2300 | F20: 350 | J20: 1000 | K20: =E20-J20-L20-M20-N20-I20+F20-P20 -> 0 | N20: 1300 | O20: -700 | P20: 350 | Q20: =Q19+N20+O20+P20 -> 10150 | R20: parking
C21: 20-22 | D21: 2 | E21: 5500 | F21: 900 | J21: 1950 | K21: =E21-J21-L21-M21-N21-I21+F21 -> 0 | N21: 4450 | O21: -700 | Q21: =Q20+N21+O21+P21 -> 13900
C22: 22-24 | D22: 2 | E22: =4100+500 -> 4600 | G22: -500 | H22: iris | J22: 1500 | K22: =E22-J22-L22-M22-N22-I22+F22 -> 0 | N22: 3100 | O22: -700 | Q22: =Q21+N22+O22+P22 -> 16300
C23: 24-26 | D23: 2 | E23: 6200 | J23: 1500 | K23: =E23-J23-L23-M23-N23-I23+F23 -> 0 | N23: 4700 | O23: -700 | Q23: =Q22+N23+O23+P23 -> 20300
C24: 26-28 | D24: 2 | E24: =2500*2 -> 5000 | H24: ma'am naicy | K24: =E24-J24-L24-M24-N24-I24+F24 -> 0 | L24: 5000 | O24: -700 | Q24: =Q23+N24+O24+P24 -> 19600
C25: 28-30 | D25: 2 | E25: 6500 | I25: 1500 | K25: =E25-J25-L25-M25-N25-I25+F25 -> 0 | N25: 5000 | O25: -700 | Q25: =Q24+N25+O25+P25 -> 23900
C26: 30-31 | D26: 1 | E26: 3000 | F26: 400 | J26: 1400 | K26: =E26-J26-L26-M26-N26-I26+F26 -> 0 | N26: 2000 | O26: -700 | Q26: =Q25+N26+O26+P26 -> 25200
C27: 31-2 | D27: 2 | E27: 7000 | J27: 2000 | K27: =E27-J27-L27-M27-N27-I27+F27 -> 0 | N27: 5000 | O27: -700 | Q27: =Q26+N27+O27+P27 -> 29500
K28: =E28-J28-L28-M28-N28-I28+F28 -> 0 | P28: -500 | Q28: =Q27+N28+O28+P28 -> 29000 | R28: grease trap
K29: =E29-J29-L29-M29-N29-I29+F29 -> 0 | P29: -5476.23 | Q29: =Q28+N29+O29+P29 -> 23523.77 | R29: Association dues
K30: =E30-J30-L30-M30-N30-I30+F30 -> 0 | P30: -2516.41 | Q30: =Q29+N30+O30+P30 -> 21007.36 | R30: Meralco
B31: DEC | C31: TOTAL | D31: =SUM(D4:D30) -> 29 | E31: =SUM(E4:E30) -> 75958.13 | F31: =SUM(F4:F30) -> 2050 | G31: =SUM(G4:G30) -> -500 | H31: =SUM(H4:H30) -> 0 | I31: =SUM(I4:I30) -> 3000 | J31: =SUM(J4:J30) -> 17350 | K31: =SUM(K4:K30) -> 0 | ... P31: =SUM(P4:P30) -> -8542.64 | Q31: =Q30 -> 21007.36
B32: JAN | C32: 45325 | D32: 1 | E32: 2300 | J32: 1000 | K32: =E32-J32-L32-M32-N32-I32+F32 -> 0 | N32: 1300 | O32: -700 | Q32: =Q31+N32+O32+P32 -> 21607.36
C33: 45720 | D33: 1 | E33: 2300 | F33: 450 | J33: 1000 | K33: =E33-J33-L33-M33-N33-I33+F33 -> 0 | N33: 1750 | O33: -700 | Q33: =Q32+N33+O33+P33 -> 22657.36
C34: 45752 | D34: 1 | E34: 2700 | J34: 1000 | K34: =E34-J34-L34-M34-N34-I34+F34 -> 0 | N34: 1700 | O34: -700 | Q34: =Q33+N34+O34+P34 -> 23657.36
C35: 45784 | D35: 2 | E35: 4000 | J35: 500 | K35: =E35-J35-L35-M35-N35-I35+F35 -> 0 | N35: 3500 | O35: -700 | Q35: =Q34+N35+O35+P35 -> 26457.36
C36: 45847 | D36: 2 | E36: 4617.2 | K36: =E36-J36-L36-M36-N36-I36+F36 -> 0 | L36: 4617.2 | O36: -700 | Q36: =Q35+N36+O36+P36 -> 25757.36
C37: 45910 | K37: =E37-J37-L37-M37-N37-I37+F37 -> 0 | Q37: =Q36+N37+O37+P37 -> 25757.36
C38: 45941 | D38: 1 | E38: 2500 | J38: 1000 | K38: =E38-J38-L38-M38-N38-I38+F38 -> 0 | N38: 1500 | O38: -700 | Q38: =Q37+N38+O38+P38 -> 26557.36
C39: 45973 | D39: 1 | E39: 3050 | J39: 1000 | K39: =E39-J39-L39-M39-N39-I39+F39 -> 0 | N39: 2050 | O39: -700 | Q39: =Q38+N39+O39+P39 -> 27907.36
C40: 46004 | D40: 1 | E40: 2575.84 | K40: =E40-J40-L40-M40-N40-I40+F40 -> 0 | L40: 2575.84 | O40: -700 | Q40: =Q39+N40+O40+P40 -> 27207.36
C41: 13-15 | K41: =E41-J41-L41-M41-N41-I41+F41 -> 0 | Q41: =Q40+N41+O41+P41 -> 27207.36
C42: 15-17 | D42: 2 | E42: 4100 | J42: 1500 | K42: =E42-J42-L42-M42-N42-I42+F42 -> 0 | N42: 2600 | O42: -700 | Q42: =Q41+N42+O42+P42 -> 29107.36
C43: 17-18 | D43: 1 | E43: 2000 | J43: 500 | K43: =E43-J43-L43-M43-N43-I43+F43 -> 0 | N43: 1500 | O43: -700 | Q43: =Q42+N43+O43+P43 -> 29907.36
C44: 18-19 | D44: 1 | E44: 2800 | J44: 1000 | K44: =E44-J44-L44-M44-N44-I44+F44 -> 0 | N44: 1800 | O44: -700 | Q44: =Q43+N44+O44+P44 -> 31007.36
C45: 19-20 | D45: 1 | E45: 2400 | F45: 400 | J45: 1000 | K45: =E45-J45-L45-M45-N45-I45+F45 -> 0 | M45: 1800 | O45: -700 | Q45: =Q44+N45+O45+P45 -> 30307.36
C46: 20-21 | D46: 1 | E46: 2300 | J46: 500 | K46: =E46-J46-L46-M46-N46-I46+F46 -> 0 | N46: 1800 | O46: -700 | Q46: =Q45+N46+O46+P46 -> 31407.36
C47: 21-22 | K47: =E47-J47-L47-M47-N47-I47+F47 -> 0 | Q47: =Q46+N47+O47+P47 -> 31407.36
C48: 22-23 | D48: 1 | E48: 1800 | F48: 350 | J48: 700 | K48: =E48-J48-L48-M48-N48-I48+F48 -> 0 | N48: 1450 | O48: -700 | Q48: =Q47+N48+O48+P48 -> 32157.36
C49: 23-24 | D49: 1 | E49: 2300 | J49: 1000 | K49: =E49-J49-L49-M49-N49-I49+F49 -> 0 | M49: 1300 | O49: -700 | Q49: =Q48+N49+O49+P49 -> 31457.36
C50: 24-25 | D50: 1 | E50: 3000 | J50: 1000 | K50: =E50-J50-L50-M50-N50-I50+F50 -> 0 | N50: 2000 | O50: -700 | Q50: =Q49+N50+O50+P50 -> 32757.36
C51: 25-27 | D51: 2 | E51: 5100 | J51: 1500 | K51: =E51-J51-L51-M51-N51-I51+F51 -> 0 | N51: 3600 | O51: -700 | Q51: =Q50+N51+O51+P51 -> 35657.36
C52: 27-28 | E52: 1250 | H52: cancelled | J52: 1250 | Q52: =Q51+N52+O52+P52 -> 35657.36 | R52: cancelled
C53: 27-28 | D53: 1 | E53: 2300 | J53: 1000 | K53: =E53-J53-L53-M53-N53-I53+F53 -> 0 | N53: 1300 | O53: -700 | Q53: =Q51+N53+O53+P53 -> 36257.36
C54: 28-29 | D54: 1 | E54: 2000 | J54: 1000 | K54: =E54-J54-L54-M54-N54-I54+F54 -> 0 | N54: 1000 | O54: -700 | Q54: =Q53+N54+O54+P54 -> 36557.36
C55: 29-30 | D55: 1 | E55: 2300 | J55: 1000 | K55: =E55-J55-L55-M55-N55-I55+F55 -> 0 | N55: 1300 | O55: -700 | Q55: =Q54+N55+O55+P55 -> 37157.36
C56: 30-31 | D56: 1 | E56: 2300 | J56: 1000 | K56: =E56-J56-L56-M56-N56-I56+F56 -> 0 | N56: 1300 | O56: -700 | Q56: =Q54+N56+O56+P56 -> 37157.36
C57: 31-1 | D57: 1 | E57: 2500 | F57: 450 | J57: 1000 | K57: =E57-J57-L57-M57-N57-I57+F57 -> 0 | M57: 1950 | O57: -700 | Q57: =Q55+N57+O57+P57 -> 36457.36
P58: -5190.19 | Q58: =Q56+N58+O58+P58 -> 31967.17 | R58: association dues
P59: 2313.7 | Q59: =Q57+N59+O59+P59 -> 38771.06 | R59: Meralco
K60: =E60-J60-L60-M60-N60-I60+F60 -> 0 | P60: -500 | Q60: =Q57+N60+O60+P60 -> 35957.36 | R60: Grease trap
K61: =E61-J61-L61-M61-N61-I61+F61 -> 0 | Q61: =Q60+N61+O61+P61 -> 35957.36
B62: JAN | C62: TOTAL | D62: =sum(D32:D61) -> 26 | E62: =SUM(E32:E61) -> 62493.04 | F62: =SUM(F32:F61) -> 1650 | G62: =SUM(G32:G61) -> 0 | H62: =SUM(H32:H61) -> 0 | I62: =SUM(I32:I61) -> 0 | J62: =SUM(J32:J61) -> 20450 | K62: =SUM(K32:K61) -> 0 | L62: =SUM(L32:L61) -> 7193.04 | ... P62: =SUM(P32:P61) -> -3376.49 | Q62: =Q61 -> 35957.36
B63: FEB | C63: 45659 | D63: 1 | E63: 2800 | J63: 1000 | K63: =E63-J63-L63-M63-N63-I63+F63 -> 0 | N63: 1800 | O63: -700 | Q63: =Q62+N63+O63+P63 -> 37057.36
C64: 45691 | D64: 2 | E64: 2500 | J64: 1000 | K64: =E64-J64-L64-M64-N64-I64+F64 -> 0 | M64: 1500 | O64: -700 | Q64: =Q63+N64+O64+P64 -> 36357.36
C65: 45720 | D65: 1 | E65: 2300 | F65: 450 | J65: 1000 | K65: =E65-J65-L65-M65-N65-I65+F65 -> 0 | M65: 1750 | O65: -700 | Q65: =Q64+N65+O65+P65 -> 35657.36
C66: 45753 | K66: =E66-J66-L66-M66-N66-I66+F66 -> 0 | Q66: =Q65+N66+O66+P66 -> 35657.36
C67: 45815 | D67: 1 | E67: 2800 | J67: 500 | K67: =E67-J67-L67-M67-N67-I67+F67 -> 0 | N67: 2300 | O67: -700 | Q67: =Q66+N67+O67+P67 -> 37257.36
C68: 45846 | D68: 1 | E68: 2850 | J68: 1200 | K68: =E68-J68-L68-M68-N68-I68+F68 -> 0 | M68: 1650 | O68: -700 | Q68: =Q67+N68+O68+P68 -> 36557.36
C69: 45879 | D69: 2 | E69: 5300 | J69: 1500 | K69: =E69-J69-L69-M69-N69-I69+F69 -> 0 | N69: 3800 | O69: -700 | Q69: =Q68+N69+O69+P69 -> 39657.36
C70: 45941 | D70: 1 | E70: =2800+500 -> 3300 | F70: 250 | J70: 1000 | K70: =E70-J70-L70-M70-N70-I70+F70 -> 0 | M70: 250 | N70: 2300 | O70: -700 | Q70: =Q69+N70+O70+P70 -> 41257.36 | R70: violation
C71: 45974 | K71: =E71-J71-L71-M71-N71-I71+F71 -> 0 | Q71: =Q70+N71+O71+P71 -> 41257.36
C72: 13-14 | D72: 1 | E72: 2300 | J72: 500 | K72: =E72-J72-L72-M72-N72-I72+F72 -> 0 | M72: 1800 | O72: -700 | Q72: =Q71+N72+O72+P72 -> 40557.36
C73: 14-15 | D73: 1 | E73: 2200 | J73: 1000 | K73: =E73-J73-L73-M73-N73-I73+F73 -> 0 | N73: 1200 | O73: -700 | Q73: =Q72+N73+O73+P73 -> 41057.36
C74: 15-16 | D74: 1 | E74: 2800 | J74: 1000 | K74: =E74-J74-L74-M74-N74-I74+F74 -> 0 | N74: 1800 | O74: -700 | Q74: =Q73+N74+O74+P74 -> 42157.36
C75: 16-17 | D75: 1 | E75: 2500 | F75: 350 | J75: 1000 | K75: =E75-J75-L75-M75-N75-I75+F75 -> 0 | N75: 1850 | O75: -700 | Q75: =Q74+N75+O75+P75 -> 43307.36
C76: 17-18 | K76: =E76-J76-L76-M76-N76-I76+F76 -> 0 | Q76: =Q75+N76+O76+P76 -> 43307.36
C77: 18-19 | D77: 1 | E77: 1886.65 | K77: =E77-J77-L77-M77-N77-I77+F77 -> 0 | L77: 1886.65 | O77: -700 | Q77: =Q76+N77+O77+P77 -> 42607.36
C78: 19-21 | D78: 2 | E78: 4100 | J78: 1500 | K78: =E78-J78-L78-M78-N78-I78+F78 -> 0 | N78: 2600 | O78: -700 | Q78: =Q77+N78+O78+P78 -> 44507.36
C79: 21-22 | D79: 1 | E79: 2500 | J79: 1000 | K79: =E79-J79-L79-M79-N79-I79+F79 -> 0 | N79: 1500 | O79: -700 | Q79: =Q78+N79+O79+P79 -> 45307.36
C80: 22-23 | D80: 1 | E80: 2800 | F80: 450 | J80: 1250 | K80: =E80-J80-L80-M80-N80-I80+F80 -> 0 | M80: 2000 | O80: -700 | Q80: =Q79+N80+O80+P80 -> 44607.36
C81: 23-24 | D81: 1 | E81: 2200 | J81: 500 | K81: =E81-J81-L81-M81-N81-I81+F81 -> 0 | N81: 1700 | O81: -700 | Q81: =Q80+N81+O81+P81 -> 45607.36
C82: 24-25 | D82: 1 | E82: 1886.65 | K82: =E82-J82-L82-M82-N82-I82+F82 -> 0 | L82: 1886.65 | O82: -700 | Q82: =Q81+N82+O82+P82 -> 44907.36
C83: 25-27 | D83: 2 | E83: 4100 | J83: 1500 | K83: =E83-J83-L83-M83-N83-I83+F83 -> 0 | N83: 2600 | O83: -700 | Q83: =Q82+N83+O83+P83 -> 46807.36
C84: 27-28 | D84: 1 | E84: 1886.65 | K84: =E84-J84-L84-M84-N84-I84+F84 -> 0 | L84: 1886.65 | O84: -700 | Q84: =Q83+N84+O84+P84 -> 46107.36
C85: 28-1 | D85: 1 | E85: 2200 | J85: 500 | K85: =E85-J85-L85-M85-N85-I85+F85 -> 0 | N85: 1700 | O85: -700 | Q85: =Q84+N85+O85+P85 -> 47107.36
K86: =E86-J86-L86-M86-N86-I86+F86 -> 0 | P86: -5662.34 | Q86: =Q85+N86+O86+P86 -> 41445.02 | R86: association dues
K87: =E87-J87-L87-M87-N87-I87+F87 -> 0 | P87: -1813.91 | Q87: =Q86+N87+O87+P87 -> 39631.11 | R87: Meralco
K88: =E88-J88-L88-M88-N88-I88+F88 -> 0 | P88: -500 | Q88: =Q87+N88+O88+P88 -> 39131.11 | R88: Grease trap
K89: =E89-J89-L89-M89-N89-I89+F89 -> 0 | P89: -39131.11 | Q89: =Q88+N89+O89+P89 -> 0
B90: FEB | C90: TOTAL | D90: =sum(D63:D89) -> 24 | E90: =SUM(E63:E89) -> 55209.95 | F90: =SUM(F63:F89) -> 1500 | G90: =SUM(G63:G89) -> 0 | H90: =SUM(H63:H89) -> 0 | I90: =SUM(I63:I89) -> 0 | J90: =SUM(J63:J89) -> 16950 | K90: =SUM(K63:K89) -> 0 | L90: =SUM(L63:L89) -> 5659.95 | ... P90: =SUM(P63:P89) -> -47107.36 | Q90: =Q89 -> 0
B91: Mar | C91: 45659 | D91: 1 | E91: 2700 | J91: 700 | K91: =E91-J91-L91-M91-N91-I91+F91 -> 0 | N91: 2000 | O91: -700 | Q91: =Q90+N91+O91+P91 -> 1300
C92: 45692 | K92: =E92-J92-L92-M92-N92-I92+F92 -> 0 | Q92: =Q91+N92+O92+P92 -> 1300
C93: 45752 | D93: 1 | E93: 2700 | J93: 1000 | K93: =E93-J93-L93-M93-N93-I93+F93 -> 0 | M93: 1700 | O93: -700 | Q93: =Q92+N93+O93+P93 -> 600
C94: 45783 | D94: 1 | E94: 1886.65 | H94: airbnb | K94: =E94-J94-L94-M94-N94-I94+F94 -> 0 | L94: 1886.65 | O94: -700 | Q94: =Q93+N94+O94+P94 -> -100
C95: 45815 | D95: 1 | E95: 2550 | J95: 1000 | K95: =E95-J95-L95-M95-N95-I95+F95 -> 0 | N95: 1550 | O95: -700 | Q95: =Q94+N95+O95+P95 -> 750
C96: 45847 | D96: 2 | E96: 5000 | J96: 1500 | K96: =E96-J96-L96-M96-N96-I96+F96 -> 0 | L96: 3500 | O96: -700 | Q96: =Q95+N96+O96+P96 -> 50
C97: 45911 | D97: 2 | E97: =200+4300 -> 4500 | J97: 1500 | K97: =E97-J97-L97-M97-N97-I97+F97 -> 0 | N97: =200+2800 -> 3000 | O97: -700 | Q97: =Q96+N97+O97+P97 -> 2350
C98: 45975 | K98: =E98-J98-L98-M98-N98-I98+F98 -> 0 | Q98: =Q97+N98+O98+P98 -> 2350
C99: 14-16 | D99: 2 | E99: 4800 | J99: 1500 | K99: =E99-J99-L99-M99-N99-I99+F99 -> 0 | M99: 3300 | O99: -700 | Q99: =Q98+N99+O99+P99 -> 1650
C100: 16-17 | D100: 1 | E100: 2300 | J100: 1000 | K100: =E100-J100-L100-M100-N100-I100+F100 -> 0 | N100: 1300 | O100: -700 | Q100: =Q99+N100+O100+P100 -> 2250
...

Sheet 828
B1: 828 BOOKING | L1: Payment | O1: 828 RECEIVABLE FROM ATE TESS
B2: Date | E2: Amount | F2: Agent's Commission | G2: Parking | H2: Remarks | I2: Reservation | K2: Balance | O2: Cleaning Fee | P2: Others | Q2: Receivable Balance | R2: Remarks
I3: BDO | J3: GCASH | L3: BDO | M3: GCASH | N3: Ate Tess
B4: DEC | C4: 45293 | D4: 1 | E4: 2300 | F4: -500 | H4: Con | J4: 500 | K4: =E4-J4-L4-M4-N4-I4+G4 -> 0 | N4: 1800 | O4: -700 | Q4: =N4+O4+P4 -> 1100 | T4: 828 | U4: =Q28 -> 14679.06
C5: 45326 | K5: =E5-J5-L5-M5-N5-I5+G5 -> 0 | Q5: =Q4+N5+O5+P5 -> 1100
C6: 4-9 | D6: 5 | E6: 9000 | G6: =800+900 -> 1700 | H6: Parking (5-7) | J6: 3000 | K6: =E6-J6-L6-M6-N6-I6+G6 -> 0 | M6: 7700 | O6: -700 | Q6: =Q5+N6+O6+P6 -> 400
C7: 45545 | D7: 1 | E7: 2100 | J7: 1000 | K7: =E7-J7-L7-M7-N7-I7+G7 -> 0 | N7: 1100 | O7: -700 | Q7: =Q6+N7+O7+P7 -> 800
C8: 45578 | E8: 500 | H8: cancelled | J8: 500 | K8: =E8-J8-L8-M8-N8-I8+G8 -> 0 | Q8: =Q7+N8+O8+P8 -> 800
C9: 13-14 | D9: 1 | E9: 2000 | K9: =E9-J9-L9-M9-N9-I9+G9 -> 0 | N9: 2000 | O9: -700 | Q9: =Q8+N9+O9+P9 -> 2100
C10: 14-16 | D10: 2 | E10: 5300 | J10: 1500 | K10: =E10-J10-L10-M10-N10-I10+G10 -> 0 | N10: 3800 | O10: -700 | Q10: =Q9+N10+O10+P10 -> 5200
C11: 16-18 | Q11: =Q10+N11+O11+P11 -> 5200
C12: 18-19 | D12: 1 | E12: 1800 | J12: 800 | K12: =E12-J12-L12-M12-N12-I12+G12 -> 0 | N12: 1000 | O12: -700 | Q12: =Q11+N12+O12+P12 -> 5500
C13: 19-20 | D13: 1 | E13: 2300 | G13: 300 | J13: 1500 | K13: =E13-J13-L13-M13-N13-I13+G13-P13 -> 0 | N13: 800 | O13: -700 | P13: 300 | Q13: =Q12+N13+O13+P13 -> 5900 | R13: Parking
C14: 20-21 | D14: 1 | E14: 2500 | J14: 1000 | K14: =E14-J14-L14-M14-N14-I14+G14 -> 0 | N14: 1500 | O14: -700 | Q14: =Q13+N14+O14+P14 -> 6700
C15: 21-22 | D15: 1 | E15: 4500 | F15: -700 | H15: con | I15: 1000 | K15: =E15-J15-L15-M15-N15-I15+G15 -> 0 | N15: 3500 | O15: -700 | P15: -500 | Q15: =Q14+N15+O15+P15 -> 9000 | R15: violation
C16: 22-23 | D16: 1 | E16: 2300 | J16: 1000 | K16: =E16-J16-L16-M16-N16-I16+G16 -> 0 | N16: 1300 | O16: -700 | Q16: =Q15+N16+O16+P16 -> 9600
C17: 23-26 | D17: 3 | E17: 9500 | J17: 2000 | K17: =E17-J17-L17-M17-N17-I17+G17 -> 0 | N17: 7500 | O17: -700 | Q17: =Q16+N17+O17+P17 -> 16400
C18: 26-28 | D18: 2 | E18: 4500 | J18: 1500 | K18: =E18-J18-L18-M18-N18-I18+G18 -> 0 | N18: 3000 | O18: -700 | Q18: =Q17+N18+O18+P18 -> 18700
C19: 28-30 | E19: 1500 | H19: cancelled | J19: 1500 | K19: =E19-J19-L19-M19-N19-I19+G19 -> 0 | Q19: =Q18+N19+O19+P19 -> 18700 | R19: cancelled
C20: 28-29 | D20: 1 | E20: 2500 | J20: 500 | K20: =E20-J20-L20-M20-N20-I20+G20 -> 0 | M20: 2000 | O20: -700 | Q20: =Q19+N20+O20+P20 -> 18000
C21: 29-30 | D21: 1 | E21: 2000 | J21: 500 | K21: =E21-J21-L21-M21-N21-I21+G21 -> 0 | N21: 1500 | O21: -700 | Q21: =Q20+N21+O21+P21 -> 18800
C22: 30-1 | E22: 1500 | H22: cancelled | J22: 1500 | K22: =E22-J22-L22-M22-N22-I22+G22 -> 0 | Q22: =Q21+N22+O22+P22 -> 18800 | R22: cancelled
C23: 31-1 | D23: 1 | E23: 2500 | J23: 1000 | K23: =E23-J23-L23-M23-N23-I23+G23 -> 0 | N23: 1500 | O23: -700 | Q23: =Q22+N23+O23+P23 -> 19600
K24: =E24-J24-L24-M24-N24-I24+G24 -> 0 | P24: -1145 | Q24: =Q23+N24+O24+P24 -> 18455 | R24: Water
K25: =E25-J25-L25-M25-N25-I25+G25 -> 0 | P25: -895.29 | Q25: =Q24+N25+O25+P25 -> 17559.71 | R25: Excss
K26: =E26-J26-L26-M26-N26-I26+G26 -> 0 | P26: -500 | Q26: =Q25+N26+O26+P26 -> 17059.71 | R26: Grease trap
K27: =E27-J27-L27-M27-N27-I27+G27 -> 0 | P27: -2380.65 | Q27: =Q26+N27+O27+P27 -> 14679.06 | R27: Meralco
B28: DEC | C28: TOTAL | D28: =sum(D4:D27) -> 23 | E28: =sum(E4:E27) -> 58600 | F28: =sum(F4:F27) -> -1200 | G28: =sum(G4:G27) -> 2000 | H28: =sum(H4:H27) -> 0 | I28: =sum(I4:I27) -> 1000 | J28: =sum(J4:J27) -> 19300 | K28: =sum(K4:K27) -> 0 | ... P28: =sum(P4:P27) -> -5120.94 | Q28: =Q27 -> 14679.06
B29: JAN | C29: 45660 | K29: =E29-J29-L29-M29-N29-I29+G29 -> 0 | Q29: =Q28+N29+O29+P29 -> 14679.06
C30: 45720 | D30: 1 | E30: 2500 | J30: 1000 | K30: =E30-J30-L30-M30-N30-I30+G30 -> 0 | M30: 1500 | O30: -700 | Q30: =Q29+N30+O30+P30 -> 13979.06
C31: 45753 | D31: 1 | E31: 2000 | K31: =E31-J31-L31-M31-N31-I31+G31 -> 0 | N31: 2000 | O31: -700 | Q31: =Q30+N31+O31+P31 -> 15279.06
C32: 45783 | K32: =E32-J32-L32-M32-N32-I32+G32 -> 0 | Q32: =Q30+N32+O32+P32 -> 13979.06
C33: 45815 | D33: 1 | E33: 2000 | J33: 1000 | K33: =E33-J33-L33-M33-N33-I33+G33 -> 0 | M33: 1000 | O33: -700 | Q33: =Q32+N33+O33+P33 -> 13279.06
C34: 45848 | K34: =E34-J34-L34-M34-N34-I34+G34 -> 0 | Q34: =Q33+N34+O34+P34 -> 13279.06
C35: 45941 | D35: 1 | E35: 2300 | J35: 500 | K35: =E35-J35-L35-M35-N35-I35+G35 -> 0 | N35: 1800 | O35: -700 | Q35: =Q34+N35+O35+P35 -> 14379.06
C36: 45973 | D36: 1 | E36: 2500 | I36: 1000 | K36: =E36-J36-L36-M36-N36-I36+G36 -> 0 | N36: 1500 | O36: -700 | Q36: =Q35+N36+O36+P36 -> 15179.06
C37: 46006 | K37: =E37-J37-L37-M37-N37-I37+G37 -> 0 | Q37: =Q36+N37+O37+P37 -> 15179.06
C38: 15-16 | D38: 1 | E38: 2300 | F38: -500 | H38: con | J38: 1000 | K38: =E38-J38-L38-M38-N38-I38+G38 -> 0 | N38: 1300 | O38: -700 | Q38: =Q37+N38+O38+P38 -> 15779.06
C39: 16-17 | K39: =E39-J39-L39-M39-N39-I39+G39 -> 0 | Q39: =Q38+N39+O39+P39 -> 15779.06
C40: 17-18 | D40: 1 | E40: 2500 | J40: 500 | K40: =E40-J40-L40-M40-N40-I40+G40 -> 0 | M40: 2000 | O40: -700 | Q40: =Q39+N40+O40+P40 -> 15079.06
C41: 18-19 | D41: 1 | E41: 2500 | J41: 1000 | K41: =E41-J41-L41-M41-N41-I41+G41 -> 0 | L41: 1500 | O41: -70 | Q41: =Q40+N41+O41+P41 -> 15009.06
C42: 19-20 | K42: =E42-J42-L42-M42-N42-I42+G42 -> 0 | Q42: =Q41+N42+O42+P42 -> 15009.06
C43: 20-21 | D43: 1 | E43: 2500 | J43: 700 | K43: =E43-J43-L43-M43-N43-I43+G43 -> 0 | M43: 1800 | O43: -700 | P43: -500 | Q43: =Q42+N43+O43+P43 -> 13809.06 | R43: violation
C44: 21-22 | D44: 1 | E44: 1800 | J44: 500 | K44: =E44-J44-L44-M44-N44-I44+G44 -> 0 | N44: 1300 | O44: -700 | Q44: =Q43+N44+O44+P44 -> 14409.06
C45: 22-23 | K45: =E45-J45-L45-M45-N45-I45+G45 -> 0 | Q45: =Q44+N45+O45+P45 -> 14409.06
C46: 23-25 | D46: 2 | E46: 5800 | J46: 1500 | K46: =E46-J46-L46-M46-N46-I46+G46 -> 0 | N46: 4300 | O46: -700 | P46: -1000 | Q46: =Q45+N46+O46+P46 -> 17009.06 | R46: violation
C47: 25-26 | E47: 1000 | H47: CANCELLED | J47: 1000 | K47: =E47-J47-L47-M47-N47-I47+G47 -> 0 | Q47: =Q46+N47+O47+P47 -> 17009.06 | R47: cancelled
C48: 25-26 | D48: 1 | E48: 2200 | J48: 500 | K48: =E48-J48-L48-M48-N48-I48+G48 -> 0 | N48: 1700 | O48: -700 | Q48: =Q47+N48+O48+P48 -> 18009.06
C49: 26-28 | D49: 2 | E49: 4000 | J49: 1000 | K49: =E49-J49-L49-M49-N49-I49+G49 -> 0 | M49: 3000 | O49: -700 | Q49: =Q48+N49+O49+P49 -> 17309.06
C50: 28-29 | K50: =E50-J50-L50-M50-N50-I50+G50 -> 0 | Q50: =Q49+N50+O50+P50 -> 17309.06
C51: 29-30 | D51: 1 | E51: 3000 | J51: 1000 | K51: =E51-J51-L51-M51-N51-I51+G51 -> 0 | M51: 2000 | O51: -700 | Q51: =Q50+N51+O51+P51 -> 16609.06
C52: 30-31 | K52: =E52-J52-L52-M52-N52-I52+G52 -> 0 | Q52: =Q51+N52+O52+P52 -> 16609.06
C53: 31-1 | D53: 1 | E53: 2000 | J53: 500 | K53: =E53-J53-L53-M53-N53-I53+G53 -> 0 | N53: 1500 | O53: -700 | Q53: =Q52+N53+O53+P53 -> 17409.06
P54: -1300 | Q54: =Q53+N54+O54+P54 -> 16109.06 | R54: Aicon cleaning
P55: -2275.76 | Q55: =Q54+N55+O55+P55 -> 13833.3 | R55: Meralco
K56: =E56-J56-L56-M56-N56-I56+G56 -> 0 | P56: -372.48 | Q56: =Q55+N56+O56+P56 -> 13460.82 | R56: Shoppee drain
K57: =E57-J57-L57-M57-N57-I57+G57 -> 0 | P57: -4000 | Q57: =Q56+N57+O57+P57 -> 9460.82 | R57: Cabinet repair
B58: JAN | C58: TOTAL | D58: =sum(D29:D57) -> 17 | E58: =sum(E29:E57) -> 40900 | F58: =sum(F29:F57) -> -500 | G58: =sum(G29:G57) -> 0 | H58: =sum(H29:H57) -> 0 | I58: =sum(I29:I57) -> 1000 | J58: =sum(J29:J57) -> 11700 | K58: =sum(K29:K57) -> 0 | ... P58: =sum(P29:P57) -> -9448.24 | Q58: =Q57 -> 9460.82 | T58: OK
B59: FEB | C59: 45659 | D59: 1 | E59: 2500 | J59: 1000 | K59: =E59-J59-L59-M59-N59-I59+G59 -> 0 | N59: 1500 | O59: -700 | Q59: =Q58+N59+O59+P59 -> 10260.82
C60: 45691 | K60: =E60-J60-L60-M60-N60-I60+G60-P60 -> 0 | Q60: =Q59+N60+O60+P60 -> 10260.82
C61: 45720 | D61: 1 | E61: =400+1800 -> 2200 | J61: 500 | K61: =E61-J61-L61-M61-N61-I61+G61 -> 0 | M61: =400+1300 -> 1700 | O61: -700 | Q61: =Q60+N61+O61+P61 -> 9560.82
C62: 45753 | K62: =E62-J62-L62-M62-N62-I62+G62 -> 0 | Q62: =Q61+N62+O62+P62 -> 9560.82
C63: 45816 | D63: 2 | E63: 3800 | J63: 1500 | K63: =E63-J63-L63-M63-N63-I63+G63 -> 0 | N63: 2300 | O63: -700 | Q63: =Q62+N63+O63+P63 -> 11160.82
C64: 45878 | D64: 1 | E64: 2500 | J64: 1000 | K64: =E64-J64-L64-M64-N64-I64+G64 -> 0 | M64: 1500 | O64: -700 | Q64: =Q63+N64+O64+P64 -> 10460.82
C65: 45910 | D65: 1 | E65: 2500 | F65: -500 | J65: 1000 | K65: =E65-J65-L65-M65-N65-I65+G65 -> 0 | M65: 1500 | O65: -700 | Q65: =Q64+N65+O65+P65 -> 9760.82
C66: 45942 | Q66: =Q65+N66+O66+P66 -> 9760.82
C67: 46004 | D67: 1 | E67: 2000 | J67: 1000 | K67: =E67-J67-L67-M67-N67-I67+G67 -> 0 | N67: 1000 | O67: -700 | Q67: =Q66+N67+O67+P67 -> 10060.82
C68: 13-14 | D68: 1 | E68: 2000 | J68: 1000 | K68: =E68-J68-L68-M68-N68-I68+G68 -> 0 | N68: 1000 | O68: -700 | Q68: =Q67+N68+O68+P68 -> 10360.82
C69: 14-15 | D69: 1 | E69: 2500 | F69: -500 | J69: 500 | K69: =E69-J69-L69-M69-N69-I69+G69 -> 0 | M69: 2000 | O69: -700 | Q69: =Q68+N69+O69+P69 -> 9660.82
C70: 15-16 | D70: 1 | E70: 2500 | J70: 1000 | K70: =E70-J70-L70-M70-N70-I70+G70 -> 0 | N70: 1500 | O70: -700 | Q70: =Q69+N70+O70+P70 -> 10460.82
C71: 16-17 | D71: 1 | E71: 2000 | G71: 300 | J71: 1000 | K71: =E71-J71-L71-M71-N71-I71+G71 -> 0 | N71: 1300 | O71: -700 | Q71: =Q70+N71+O71+P71 -> 11060.82
C72: 17-18 | K72: =E72-J72-L72-M72-N72-I72+G72 -> 0 | Q72: =Q71+N72+O72+P72 -> 11060.82
C73: 18-20 | D73: 2 | E73: 3500 | G73: 600 | J73: 1800 | K73: =E73-J73-L73-M73-N73-I73+G73 -> 0 | N73: 2300 | O73: -700 | Q73: =Q72+N73+O73+P73 -> 12660.82
C74: 20-21 | K74: =E74-J74-L74-M74-N74-I74+G74 -> 0 | Q74: =Q73+N74+O74+P74 -> 12660.82
C75: 21-22 | D75: 1 | E75: 2000 | J75: 500 | K75: =E75-J75-L75-M75-N75-I75+G75 -> 0 | M75: 1500 | O75: -700 | Q75: =Q74+N75+O75+P75 -> 11960.82
C76: 22-23 | D76: 1 | E76: 2750 | J76: 1000 | K76: =E76-J76-L76-M76-N76-I76+G76 -> 0 | N76: 1750 | O76: -700 | Q76: =Q75+N76+O76+P76 -> 13010.82
C77: 23-28 | D77: 5 | E77: =5300+3000 -> 8300 | G77: =1150+800 -> 1950 | J77: 1500 | K77: =E77-J77-L77-M77-N77-I77+G77 -> 0 | N77: =3800+1150+3800 -> 8750 | O77: -700 | Q77: =Q76+N77+O77+P77 -> 21060.82
C78: 28-1 | D78: 1 | E78: 1800 | G78: 350 | J78: 500 | K78: =E78-J78-L78-M78-N78-I78+G78 -> 0 | N78: 1650 | O78: -700 | Q78: =Q77+N78+O78+P78 -> 22010.82
P79: -500 | Q79: =Q78+N79+O79+P79 -> 21510.82 | R79: Grease trap
K80: =E80-J80-L80-M80-N80-I80+G80 -> 0 | P80: -2142.41 | Q80: =Q79+N80+O80+P80 -> 19368.41 | R80: Meralco
K81: =E81-J81-L81-M81-N81-I81+G81 -> 0 | P81: -19368.41 | Q81: =Q80+N81+O81+P81 -> 0 | R81: Meralco
B82: FEB | C82: TOTAL | D82: =sum(D59:D81) -> 21 | E82: =sum(E59:E81) -> 42850 | F82: =sum(F59:F81) -> -1000 | G82: =sum(G59:G81) -> 3200 | H82: =sum(H59:H81) -> 0 | I82: =sum(I59:I81) -> 0 | J82: =sum(J59:J81) -> 14800 | K82: =sum(K59:K81) -> 0 | ... P82: =sum(P59:P81) -> -22010.82 | Q82: =Q81 -> 0
B83: MAR | C83: 45660 | D83: 2 | E83: 4700 | J83: 1500 | K83: =E83-J83-L83-M83-N83-I83+G83 -> 0 | N83: 3200 | O83: -700 | Q83: =Q82+N83+O83+P83 -> 2500
C84: 45722 | K84: =E84-J84-L84-M84-N84-I84+G84-P84 -> 0 | Q84: =Q83+N84+O84+P84 -> 2500
C85: 45815 | D85: 1 | E85: =2450+500 -> 2950 | J85: 1000 | K85: =E85-J85-L85-M85-N85-I85+G85 -> 0 | N85: 1950 | O85: -700 | P85: -500 | Q85: =Q84+N85+O85+P85 -> 3250 | R85: 500 violation
C86: 45846 | D86: 1 | E86: 2200 | G86: 450 | J86: 1250 | K86: =E86-J86-L86-M86-N86-I86+G86 -> 0 | M86: 1400 | O86: -700 | Q86: =Q85+N86+O86+P86 -> 2550
C87: 45878 | D87: 1 | E87: 2500 | G87: 350 | J87: 1200 | K87: =E87-J87-L87-M87-N87-I87+G87 -> 0 | N87: 1650 | O87: -700 | Q87: =Q86+N87+O87+P87 -> 3500
C88: 45911 | K88: =E88-J88-L88-M88-N88-I88+G88 -> 0 | Q88: =Q87+N88+O88+P88 -> 3500
C89: 45974 | D89: 2 | E89: 2792.82 | K89: =E89-J89-L89-M89-N89-I89+G89 -> 0 | L89: 2792.82 | O89: -700 | Q89: =Q88+N89+O89+P89 -> 2800
C90: 13-14 | Q90: =Q89+N90+O90+P90 -> 2800
C91: 14-15 | D91: 1 | E91: 2000 | J91: 500 | K91: =E91-J91-L91-M91-N91-I91+G91 -> 0 | M91: 1500 | O91: -700 | Q91: =Q90+N91+O91+P91 -> 2100
C92: 15-16 | D92: 1 | E92: 2500 | J92: 1000 | K92: =E92-J92-L92-M92-N92-I92+G92 -> 0 | N92: 1500 | O92: -700 | Q92: =Q91+N92+O92+P92 -> 2900
C93: 16-18 | D93: 2 | E93: 4700 | J93: 1500 | K93: =E93-J93-L93-M93-N93-I93+G93 -> 0 | N93: 3200 | O93: -700 | Q93: =Q92+N93+O93+P93 -> 5400
C94: 18-22 | K94: =E94-J94-L94-M94-N94-I94+G94 -> 0 | O94: -700 | Q94: =Q93+N94+O94+P94 -> 4700 | R94: katth and jay
C95: 22-23 | D95: 1 | E95: 2500 | J95: 1000 | K95: =E95-J95-L95-M95-N95-I95+G95 -> 0 | M95: 1500 | O95: -700 | Q95: =Q94+N95+O95+P95 -> 4000
C96: 23-25 | K96: =E96-J96-L96-M96-N96-I96+G96 -> 0 | Q96: =Q95+N96+O96+P96 -> 4000
C97: 25-26 | D97: 1 | E97: =400+2000 -> 2400 | J97: 1000 | K97: =E97-J97-L97-M97-N97-I97+G97 -> 0 | N97: =400+1000 -> 1400 | O97: -700 | Q97: =Q96+N97+O97+P97 -> 4700
C98: 26-29 | K98: =E98-J98-L98-M98-N98-I98+G98 -> 0 | Q98: =Q97+N98+O98+P98 -> 4700
C99: 29-30 | D99: 1 | E99: 2500 | J99: 1000 | K99: =E99-J99-L99-M99-N99-I99+G99 -> 0 | M99: 1500 | O99: -700 | Q99: =Q98+N99+O99+P99 -> 4000
C100: 30-1 | K100: =E100-J100-L100-M100-N100-I100+G100 -> 0 | Q100: =Q99+N100+O100+P100 -> 4000
...

Sheet 105
B1: 105 BOOKING | L1: Full payment | P1: 105 RECEIVABLE FROM ATE CZARINA
B2: Date | E2: Amount | F2: Parking | G2: Agent's Commissions | H2: Remarks | I2: Reservation | K2: Balance | O2: Cleaning Fee | P2: Others | Q2: Receivable Balance | R2: Remarks
I3: Gcash | J3: BDO | L3: BDO | M3: GCASH | N3: Ate CZARINA
B4: Feb | C4: 13-14 | D4: 1 | E4: 1500 | I4: 500 | K4: =E4-I4-L4-M4-N4-J4+F4 -> 0 | M4: 1000 | O4: -500 | Q4: =Q3+N4+O4+P4 -> -500
C5: 14-15 | D5: 1 | E5: 2200 | J5: 1000 | K5: =E5-I5-L5-M5-N5-J5+F5 -> 0 | N5: 1200 | O5: -500 | Q5: =Q4+N5+O5+P5 -> 200
C6: 15-16 | D6: 1 | E6: 2000 | I6: 700 | K6: =E6-I6-L6-M6-N6-J6+F6 -> 1 | N6: 1299 | O6: -500 | Q6: =Q5+N6+O6+P6 -> 999
C7: 16-17 | D7: 1 | E7: 2000 | I7: 1000 | K7: =E7-I7-L7-M7-N7-J7+F7 -> 0 | N7: 1000 | O7: -500 | Q7: =Q6+N7+O7+P7 -> 1499
C8: 17-18 | K8: =E8-I8-L8-M8-N8-J8+F8 -> 0 | Q8: =Q7+N8+O8+P8 -> 1499
C9: 18-20 | D9: 2 | E9: 3300 | I9: 1500 | K9: =E9-I9-L9-M9-N9-J9+F9 -> 0 | M9: 1800 | O9: -500 | Q9: =Q8+N9+O9+P9 -> 999
C10: 20-21 | K10: =E10-I10-L10-M10-N10-J10+F10 -> 0 | Q10: =Q9+N10+O10+P10 -> 999
C11: 21-22 | D11: 1 | E11: 2000 | I11: 1000 | K11: =E11-I11-L11-M11-N11-J11+F11 -> 0 | N11: 1000 | O11: -500 | Q11: =Q10+N11+O11+P11 -> 1499
C12: 22-23 | D12: 1 | E12: 2500 | G12: -200 | I12: 500 | K12: =E12-I12-L12-M12-N12-J12+F12 -> 0 | M12: 2000 | O12: -500 | Q12: =Q11+N12+O12+P12 -> 999
C13: 23-25 | D13: 2 | E13: 3300 | K13: =E13-I13-L13-M13-N13-J13+F13 -> 0 | M13: 3300 | O13: -500 | Q13: =Q12+N13+O13+P13 -> 499
K14: =E14-I14-L14-M14-N14-J14+F14 -> 0 | Q14: =Q13+N14+O14+P14 -> 499
K15: =E15-I15-L15-M15-N15-J15+F15 -> 0 | Q15: =Q14+N15+O15+P15 -> 499
C16: 28-2 | D16: 2 | E16: 3317.4 | G16: =50+400 -> 450 | H16: airbnb | K16: =E16-I16-L16-M16-N16-J16+F16 -> 0 | L16: 3317.4 | O16: -500 | Q16: =Q15+N16+O16+P16 -> -1
P17: -500 | Q17: =Q16+N17+O17+P17 -> -501 | R17: Cleaning
P18: -500 | Q18: =Q17+N18+O18+P18 -> -1001 | R18: Laundry
P19: 1001 | Q19: =Q18+N19+O19+P19 -> 0
B20: Feb | C20: Total | D20: =sum(D4:D18) -> 12 | E20: =sum(E4:E18) -> 22117.4 | G20: =sum(G4:G18) -> 250 | I20: =sum(I4:I18) -> 5200 | J20: =sum(J4:J18) -> 1000 | K20: =sum(K4:K18) -> 1 | L20: =sum(L4:L18) -> 3317.4 | M20: =sum(M4:M18) -> 8100 | N20: =sum(N4:N18) -> 4499 | O20: =sum(O4:O18) -> -4500 | P20: =sum(P4:P19) -> 1 | Q20: =Q19 -> 0
B21: Mar | C21: 45691 | D21: 1 | E21: 2000 | I21: 1000 | K21: =E21-I21-L21-M21-N21-J21+F21 -> 0 | N21: 1000 | O21: -500 | Q21: =Q20+N21+O21+P21 -> 500
C22: 45720 | K22: =E22-I22-L22-M22-N22-J22+F22 -> 0 | Q22: =Q21+N22+O22+P22 -> 500
C23: 45752 | D23: 1 | E23: 1999 | I23: 500 | K23: =E23-I23-L23-M23-N23-J23+F23 -> 0 | N23: 1499 | O23: -500 | Q23: =Q22+N23+O23+P23 -> 1499
C24: 45783 | D24: 1 | E24: 1600 | I24: 500 | K24: =E24-I24-L24-M24-N24-J24+F24 -> 0 | N24: 1100 | O24: -500 | Q24: =Q23+N24+O24+P24 -> 2099
C25: 45815 | K25: =E25-I25-L25-M25-N25-J25+F25 -> 0 | Q25: =Q24+N25+O25+P25 -> 2099
C26: 45847 | D26: 2 | E26: 3900 | I26: 1500 | K26: =E26-I26-L26-M26-N26-J26+F26 -> 0 | N26: 2400 | O26: -500 | Q26: =Q25+N26+O26+P26 -> 3999
C27: 45916 | D27: 7 | E27: 11900 | I27: 4000 | K27: =E27-I27-L27-M27-N27-J27+F27 -> 0 | N27: 7900 | O27: -500 | Q27: =Q26+N27+O27+P27 -> 11399
C28: 16-22 | Q28: =Q27+N28+O28+P28 -> 11399
C29: 22-24 | D29: 2 | E29: 3084.6 | K29: =E29-I29-L29-M29-N29-J29+F29 -> 0 | L29: 3084.6 | O29: -500 | Q29: =Q28+N29+O29+P29 -> 10899
C30: 24-25 | D30: 1 | E30: 1800 | K30: =E30-I30-L30-M30-N30-J30+F30 -> 0 | N30: 1800 | O30: -500 | Q30: =Q29+N30+O30+P30 -> 12199
C31: 25-26 | D31: 1 | E31: 1800 | I31: 1000 | K31: =E31-I31-L31-M31-N31-J31+F31 -> 0 | N31: 800 | O31: -500 | Q31: =Q30+N31+O31+P31 -> 12499
C32: 26-28 | K32: =E32-I32-L32-M32-N32-J32+F32 -> 0 | Q32: =Q31+N32+O32+P32 -> 12499
C33: 28-29 | D33: 1 | E33: 2100 | F33: 350 | I33: 1200 | K33: =E33-I33-L33-M33-N33-J33+F33 -> 0 | N33: 1250 | O33: -500 | Q33: =Q32+N33+O33+P33 -> 13249
C34: 29-31 | D34: 2 | E34: 4100 | I34: 1500 | K34: =E34-I34-L34-M34-N34-J34+F34 -> 0 | N34: 2600 | O34: -500 | Q34: =Q33+N34+O34+P34 -> 15349
C35: 31-2 | D35: 2 | E35: 3900 | I35: 1500 | N35: 2400 | O35: -500 | Q35: =Q34+N35+O35+P35 -> 17249
P36: -849 | Q36: =Q35+N36+O36+P36 -> 16400 | R36: Bidet
K37: =E37-I37-L37-M37-N37-J37+F37 -> 0 | P37: -909.4 | Q37: =Q36+N37+O37+P37 -> 15490.6 | R37: water
P38: -3163.61 | Q38: =Q37+N38+O38+P38 -> 12326.99 | R38: meralco | T38: 909.4
P39: -500 | Q39: =Q38+N39+O39+P39 -> 11826.99 | R39: grease trap
P40: -150 | Q40: =Q39+N40+O40+P40 -> 11676.99 | R40: Bidet replace
P41: -11676.99 | Q41: =Q40+N41+O41+P41 -> 0
B42: Mar | C42: Total | D42: =sum(D21:D37) -> 21 | E42: =sum(E21:E37) -> 38183.6 | G42: =sum(G21:G37) -> 0 | I42: =sum(I21:I37) -> 12700 | J42: =sum(J21:J37) -> 0 | K42: =sum(K21:K37) -> 0 | L42: =sum(L21:L37) -> 3084.6 | M42: =sum(M21:M37) -> 0 | N42: =sum(N21:N37) -> 22749 | O42: =sum(O21:O37) -> -5500 | P42: =sum(P21:P38) -> -4922.01 | Q42: =Q41 -> 0 | T42: 3163.61
B43: Apr | C43: 45693 | K43: =E43-I43-L43-M43-N43-J43+F43 -> 0 | Q43: =Q42+N43+O43+P43 -> 0
B44: Apr | C44: 45784 | D44: 2 | E44: =2300+1500 -> 3800 | I44: 1000 | K44: =E44-I44-L44-M44-N44-J44+F44 -> 0 | M44: 1500 | N44: 1300 | O44: -500 | Q44: =Q43+N44+O44+P44 -> 800
C45: 45849 | K45: =E45-I45-L45-M45-N45-J45+F45 -> 0 | Q45: =Q44+N45+O45+P45 -> 800
C46: 45973 | D46: 1 | E46: 1500 | I46: 500 | K46: =E46-I46-L46-M46-N46-J46+F46 -> 0 | N46: 1000 | O46: -500 | Q46: =Q45+N46+O46+P46 -> 1300
C47: 46004 | D47: 1 | E47: 2300 | I47: 1000 | K47: =E47-I47-L47-M47-N47-J47+F47 -> 0 | N47: 1300 | O47: -500 | Q47: =Q46+N47+O47+P47 -> 2100
C48: 13-14 | Q48: =Q47+N48+O48+P48 -> 2100
C49: 14-15 | D49: 1 | E49: 1900 | I49: 900 | K49: =E49-I49-L49-M49-N49-J49+F49 -> 0 | N49: 1000 | O49: -500 | Q49: =Q48+N49+O49+P49 -> 2600
C50: 15-16 | K50: =E50-I50-L50-M50-N50-J50+F50 -> 0 | Q50: =Q49+N50+O50+P50 -> 2600
C51: 16-17 | D51: 1 | E51: 1700 | I51: 900 | K51: =E51-I51-L51-M51-N51-J51+F51 -> 0 | N51: 800 | O51: -500 | Q51: =Q50+N51+O51+P51 -> 2900
C52: 17-18 | D52: 1 | E52: 2500 | I52: 1000 | K52: =E52-I52-L52-M52-N52-J52+F52 -> 0 | N52: 1500 | O52: -500 | Q52: =Q51+N52+O52+P52 -> 3900
C53: 18-20 | D53: 2 | E53: 4700 | I53: 1500 | K53: =E53-I53-L53-M53-N53-J53+F53 -> 0 | N53: 3200 | O53: -500 | Q53: =Q52+N53+O53+P53 -> 6600
C54: 20-22 | K54: =E54-I54-L54-M54-N54-J54+F54 -> 0 | Q54: =Q53+N54+O54+P54 -> 6600
C55: 22-23 | D55: 1 | E55: 1600 | I55: 600 | K55: =E55-I55-L55-M55-N55-J55+F55 -> 0 | N55: 1000 | O55: -500 | Q55: =Q54+N55+O55+P55 -> 7100
C56: 23-24 | K56: =E56-I56-L56-M56-N56-J56+F56 -> 0 | Q56: =Q55+N56+O56+P56 -> 7100
C57: 24-25 | D57: 1 | E57: 2100 | F57: 450 | I57: 1000 | K57: =E57-I57-L57-M57-N57-J57+F57 -> 0 | N57: 1550 | O57: -500 | Q57: =Q56+N57+O57+P57 -> 8150
C58: 25-26 | D58: 1 | E58: 1000 | H58: cancelled | I58: 1000 | K58: =E58-I58-L58-M58-N58-J58+F58 -> 0 | Q58: =Q57+N58+O58+P58 -> 8150 | R58: cancelled
C59: 26-28 | D59: 2 | E59: 4100 | I59: 1500 | K59: =E59-I59-L59-M59-N59-J59+F59 -> 0 | N59: 2600 | O59: -500 | Q59: =Q58+N59+O59+P59 -> 10250
C60: 28-30 | D60: 2 | E60: 3200 | F60: 450 | I60: 1500 | K60: =E60-I60-L60-M60-N60-J60+F60 -> 0 | M60: 2150 | O60: -500 | Q60: =Q59+N60+O60+P60 -> 9750
C61: 30-1 | D61: 1 | E61: 1900 | I61: 1000 | K61: =E61-I61-L61-M61-N61-J61+F61 -> 0 | N61: 900 | O61: -500 | Q61: =Q60+N61+O61+P61 -> 10150
K62: =E62-I62-L62-M62-N62-J62+F62 -> 0 | P62: -1751.42 | Q62: =Q61+N62+O62+P62 -> 8398.58 | R62: water
K63: =E63-I63-L63-M63-N63-J63+F63 -> 0 | P63: -2233.53 | Q63: =Q62+N63+O63+P63 -> 6165.05 | R63: meralco
K64: =E64-I64-L64-M64-N64-J64+F64 -> 0 | P64: -6165.05 | Q64: =Q63+N64+O64+P64 -> 0
B65: Apr | C65: Total | D65: =sum(D43:D61) -> 17 | E65: =sum(E43:E61) -> 32300 | G65: =sum(G43:G61) -> 0 | I65: =sum(I43:I61) -> 13400 | J65: =sum(J43:J61) -> 0 | K65: =sum(K43:K61) -> 0 | L65: =sum(L43:L61) -> 0 | M65: =sum(M43:M61) -> 3650 | N65: =sum(N43:N61) -> 16150 | O65: =sum(O43:O61) -> -6000 | P65: =sum(P43:P61) -> 0 | Q65: =Q64 -> 0 | T65: 3163.61
B66: May | C66: 45660 | D66: 2 | E66: 3500 | I66: 1500 | K66: =E66-I66-L66-M66-N66-J66+F66 -> 0 | N66: 2000 | O66: -500 | Q66: =+N66+O66+P66 -> 1500
C67: 45721 | D67: 2 | E67: 3317.4 | J67: 3317.4 | K67: =E67-I67-L67-M67-N67-J67+F67 -> 0 | O67: -500 | Q67: =Q66+N67+O67+P67 -> 1000
C68: 45787 | K68: =E68-I68-L68-M68-N68-J68+F68 -> 0 | Q68: =Q67+N68+O68+P68 -> 1000
C69: 45942 | D69: 2 | E69: 4400 | I69: 1500 | K69: =E69-I69-L69-M69-N69-J69+F69 -> 0 | N69: 2900 | O69: -500 | Q69: =Q68+N69+O69+P69 -> 3400
C70: 46004 | Q70: =Q69+N70+O70+P70 -> 3400
C71: 13-15 | D71: 2 | E71: 3300 | I71: 1500 | K71: =E71-I71-L71-M71-N71-J71+F71 -> 0 | N71: 1800 | O71: -500 | Q71: =Q70+N71+O71+P71 -> 4700
C72: 15-17 | K72: =E72-I72-L72-M72-N72-J72+F72 -> 0 | Q72: =Q71+N72+O72+P72 -> 4700
C73: 17-19 | D73: 2 | E73: 4300 | I73: 1500 | K73: =E73-I73-L73-M73-N73-J73+F73 -> 0 | N73: 2800 | O73: -500 | Q73: =Q72+N73+O73+P73 -> 7000
C74: 19-20 | D74: 1 | E74: 1600 | K74: =E74-I74-L74-M74-N74-J74+F74 -> 0 | N74: 1600 | O74: -500 | Q74: =Q73+N74+O74+P74 -> 8100
C75: 20-21 | D75: 1 | E75: 1600 | I75: 1000 | K75: =E75-I75-L75-M75-N75-J75+F75 -> 0 | N75: 600 | O75: -500 | Q75: =Q74+N75+O75+P75 -> 8200
C76: 21-22 | K76: =E76-I76-L76-M76-N76-J76+F76 -> 0 | Q76: =Q75+N76+O76+P76 -> 8200
C77: 22-24 | D77: 2 | E77: 3600 | I77: 1500 | K77: =E77-I77-L77-M77-N77-J77+F77 -> 0 | N77: 2100 | O77: -500 | Q77: =Q76+N77+O77+P77 -> 9800
C78: 24-25 | D78: 1 | E78: =3000-450 -> 2550 | F78: 450 | I78: 1250 | K78: =E78-I78-L78-M78-N78-J78+F78 -> 0 | N78: 1750 | O78: -500 | Q78: =Q77+N78+O78+P78 -> 11050
C79: 25-28 | K79: =E79-I79-L79-M79-N79-J79+F79 -> 0 | Q79: =Q78+N79+O79+P79 -> 11050
C80: 28-30 | D80: 2 | E80: 3400 | I80: 1500 | K80: =E80-I80-L80-M80-N80-J80+F80 -> 0 | N80: 1900 | O80: -500 | Q80: =Q79+N80+O80+P80 -> 12450
C81: 30-2 | D81: 2 | E81: 6000 | I81: 1500 | K81: =E81-I81-L81-M81-N81-J81+F81 -> 0 | M81: 1700 | N81: =2800 -> 2800 | O81: -500 | Q81: =Q80+N81+O81+P81 -> 14750
K82: =E82-I82-L82-M82-N82-J82+F82 -> 0 | P82: -634.16 | Q82: =Q81+N82+O82+P82 -> 14115.84 | R82: water
K83: =E83-I83-L83-M83-N83-J83+F83 -> 0 | P83: -3379.22 | Q83: =Q82+N83+O83+P83 -> 10736.62 | R83: meralco
K84: =E84-I84-L84-M84-N84-J84+F84 -> 0 | P84: -10736.62 | Q84: =Q83+N84+O84+P84 -> 0
B85: MAY | C85: Total | D85: =sum(D66:D81) -> 19 | E85: =sum(E66:E81) -> 37567.4 | G85: =sum(G66:G81) -> 0 | I85: =sum(I66:I81) -> 12750 | J85: =sum(J66:J81) -> 3317.4 | K85: =sum(K66:K81) -> 0 | L85: =sum(L66:L81) -> 0 | M85: =sum(M66:M81) -> 1700 | N85: =sum(N66:N81) -> 20250 | O85: =sum(O66:O81) -> -5500 | P85: =sum(P66:P81) -> 0 | Q85: =Q84 -> 0 | T85: 3163.61
B86: JUN | C86: 45694 | K86: =E86-I86-L86-M86-N86-J86+F86 -> 0 | Q86: =Q85 -> 0
C87: 45815 | D87: 1 | E87: 2200 | I87: 1000 | K87: =E87-I87-L87-M87-N87-J87+F87 -> 0 | N87: 1200 | O87: -500 | Q87: =Q86+N87+O87+P87 -> 700
C88: 45846 | D88: 1 | E88: 2300 | I88: 1000 | K88: =E88-I88-L88-M88-N88-J88+F88 -> 0 | N88: 1300 | O88: -500 | Q88: =Q87+N88+O88+P88 -> 1500
C89: 45881 | K89: =E89-I89-L89-M89-N89-J89+F89 -> 0 | Q89: =Q88+N89+O89+P89 -> 1500
C90: 46004 | D90: 1 | E90: 2100 | I90: 1000 | K90: =E90-I90-L90-M90-N90-J90+F90 -> 0 | N90: 1100 | O90: -500 | Q90: =Q89+N90+O90+P90 -> 2100
C91: 13-15 | D91: 1 | E91: 3900 | I91: 1500 | K91: =E91-I91-L91-M91-N91-J91+F91 -> 0 | N91: 2400 | O91: -500 | Q91: =Q90+N91+O91+P91 -> 4000
C92: 15-16 | K92: =E92-I92-L92-M92-N92-J92+F92 -> 0 | Q92: =Q91+N92+O92+P92 -> 4000
C93: 16-17 | D93: 1 | E93: 1500 | I93: 700 | K93: =E93-I93-L93-M93-N93-J93+F93 -> 0 | N93: 800 | O93: -500 | Q93: =Q92+N93+O93+P93 -> 4300
C94: 17-18 | D94: 1 | E94: 1850 | I94: 500 | K94: =E94-I94-L94-M94-N94-J94+F94 -> 0 | N94: 1350 | O94: -500 | Q94: =Q93+N94+O94+P94 -> 5150
C95: 18-19 | K95: =E95-I95-L95-M95-N95-J95+F95 -> 0 | Q95: =Q94+N95+O95+P95 -> 5150
C96: 19-20 | D96: 1 | E96: 1700 | I96: 800 | K96: =E96-I96-L96-M96-N96-J96+F96 -> 0 | N96: 900 | O96: -500 | Q96: =Q95+N96+O96+P96 -> 5550
C97: 20-21 | K97: =E97-I97-L97-M97-N97-J97+F97 -> 0 | Q97: =Q96+N97+O97+P97 -> 5550
C98: 21-22 | D98: 1 | E98: 2300 | J98: 1000 | K98: =E98-I98-L98-M98-N98-J98+F98 -> 0 | N98: 1300 | O98: -500 | Q98: =Q97+N98+O98+P98 -> 6350
C99: 22-24 | K99: =E99-I99-L99-M99-N99-J99+F99 -> 0 | Q99: =Q98+N99+O99+P99 -> 6350
C100: 24-27 | D100: 3 | E100: 4700 | I100: 2000 | K100: =E100-I100-L100-M100-N100-J100+F100 -> 0 | M100: 2700 | O100: -500 | Q100: =Q99+N100+O100+P100 -> 5850
...

Sheet Summary
B2: Ate Tess Summary | G2: Ate Czarina Summary
B3: December- February Balance | G3: February
C4: 1228 | D4: 278.03 | H4: 105 | J4: -1001
C5: 1127 | D5: 23000.15 | H5: 635 | J5: 12404.5
C6: 1230 | D6: 39131.11 | H6: 1931 | J6: 12230.94
C7: 828 | D7: 19368.41 | H7: Total | J7: =J4+J6+J5 -> 23634.44
B8: Total | D8: =D4+D5+D6+D7 -> 81777.7 | H8: Foam | J8: -1999
B9: January Deposit | D9: 60000 | H9: battery | J9: -159
B10: Balance | D10: =D8-D9 -> 21777.7 | H10: 1231 internet | J10: 850
B11: assoc dues 828 | D11: -9610.18 | H11: Balance | J11: =sum(J7:J10) -> 22326.44
B12: Water Heater | D12: -5550
B13: February | D13: =D10+D11+D12 -> 6617.52 | G13: March | H13: 105 | J13: 16400
H14: 635 | J14: 19799
H15: 1931 | J15: 15249
H16: Total | J16: =sum(J13:J15) -> 51448
B17: March to May Balance | H17: Less: | J17: =sum(I18:I29) -> 18562.97
C18: 1228 | D18: 4847.78 | H18: 1931 meralco | I18: 3766.42
C19: 1127 | D19: 213.59 | H19: 1931 Assoc dues | I19: 6260.74
C20: 1230 | D20: -191.04 | H20: 635 water | I20: 1059.8
C21: 828 | D21: 4009.27 | H21: 105 water | I21: 909.4 | M21: =450*8 -> 3600
B22: Total | D22: =D18+D19+D20+D21 -> 8879.6 | H22: 105 meralco | I22: 3163.61 | M22: 1500
H23: bidet 105 | I23: 150
D24: =D22-9000 -> -120.4 | H24: bidet 635 | I24: 150
H25: grease trap | I25: 500
B26: Jun to July | I26: 500
C27: 1228 | D27: -3547.29 | E27: ='1228'!Q181 -> -8492.6 | F27: =D27-E27 -> 4945.31 | I27: 500
C28: 1127 | D28: 73.25 | E28: ='1127'!Q191 -> 73.25 | F28: =D28-E28 -> 0 | H28: Aircon | I28: 1500
C29: 1230 | D29: 3165.77 | E29: ='1230'!Q231 -> -434.23 | F29: =D29-E29 -> 3600 | H29: bulb | I29: 103
C30: 828 | D30: 1069.9 | E30: ='828'!Q199 -> 1069.902 | F30: =D30-E30 -> -0.002 | H30: Total | J30: =J16-J17 -> 32885.03
B31: Total | D31: =SUM(D27:D30) -> 761.63 | H31: 1231 internet | J31: 850
H32: Total | J32: =J30+J31 -> 33735.03
G34: April | H34: 105 | J34: ='105'!Q65 -> 0
H35: 635 | J35: ='635'!Q74 -> 0
H36: 1931 | J36: ='1931'!Q122 -> 0
B37: October 2025 to Mar 2026 | H37: Total | J37: =sum(J34:J36) -> 0
B38: 828 | C38: ='828'!Q335 -> -11828.278 | H38: 1231 internet | J38: 850
B39: 1230 | C39: ='1230'!Q415 -> -20077.93 | H39: Total | J39: =J37+J38 -> 850
B40: 1228 | C40: ='1228'!Q350 -> 21652.37 | H40: Supplies | J40: -1352.25
B41: 1127 | C41: ='1127'!Q374 -> 12397.9 | H41: Grease trap | J41: -500
B42: Total | C42: =SUM(C38:C41) -> 2144.062 | H42: MOP | J42: =-475*3 -> -1425
B43: Summary April to June | H43: body wash | J43: =-334-299 -> -633
B44: 1127 | C44: ='1127'!Q446 -> 0 | H44: Total | J44: =sum(J39:J43) -> -3060.25
B45: 1230 | C45: ='1230'!Q493 -> 0 | G45: May | H45: 105 | J45: 10736.62
B46: 1228 | C46: ='1228'!Q417 -> 0 | H46: 635 | J46: 19149
B47: Total | C47: =C44+C45+C46 -> 0 | H47: 1931 | J47: 9293.31
H48: Total | J48: =sum(J45:J47) -> 39178.93 | M48: 1228 | N48: 6618.66
B49: Grand total | C49: =C42+C47 -> 2144.062 | H49: Parking | I49: unit 635 | J49: 450 | M49: 1127 | N49: 7030.33
H50: Total | J50: =sum(J48:J49) -> 39628.93 | M50: 1230 | N50: 5761.7
G51: June | H51: 105 | J51: 5296.36 | N51: =sum(N48:N50) -> 19410.69
H52: 635 | J52: 14749 | N52: =C57+J193 -> 17779.81
B53: July to Aug | H53: 1931 | J53: 1565
B54: 1230 | C54: ='1230'!Q543 -> -5691.17 | H54: Total | J54: =sum(J51:J53) -> 21610.36
B55: 1228 | C55: ='1228'!Q476 -> -2533 | H55: 1931 Association Dues | J55: -4017.79
B56: 1127 | C56: ='1127'!Q491 -> 11991.67 | H56: 105 water | J56: -140
B57: Total | C57: =SUM(C54:C56) -> 3767.5 | H57: Grease trap | J57: -1000
H58: Doormat | J58: -506.01
H59: Total | J59: =sum(J54:J58) -> 15946.56
G60: July | H60: 105 | J60: -8224.01 | K60: ='105'!Q126 -> 0
H61: 635 | J61: 20725 | K61: ='635'!Q141 -> 0
H62: 1931 | J62: -725.43 | K62: ='1931'!Q203 -> 0
H63: Total | J63: =sum(J60:J62) -> 11775.56
H64: 105 GAF (07/03) | J64: -140
H65: Lare chek in | J65: -200
H66: 105 meralco | J66: -2771.35
H67: shampoo/soap | J67: -841.33
H68: Total | J68: =sum(J63:J67) -> 7822.88
H69: Parking 105 (July 30) | J69: 400
H70: Grand total | J70: =sum(J68:J69) -> 8222.88
G71: Aug | H71: Summary
H72: 1931 | I72: =D80 | J72: ='1931'!V216 -> 0
H73: 635 | I73: ='635'!D19 | J73: ='1931'!V217 -> 0
H74: 105 | I74: ='105'!D3 | J74: ='1931'!V218 -> 0
H75: Total | J75: =sum(J72:J74) -> 0
H76: Less
H77: 1931 Meralco | I77: -2555.42 | O77: ±±
H78: 105 assoc | I78: -3094.76
H79: Supplies | I79: -1352.25 | J79: =sum(I77:I79) -> -7002.43
H80: Total | J80: =sum(J75:J79) -> -7002.43
H81: remittance | J81: 25000
H82: Balance | J82: =J80-J81 -> -32002.43
G84: Sept | H84: Summary
H85: 1931 | J85: ='1931'!Q244 -> 6999
H86: 635 | J86: ='635'!Q177 -> 12274
H87: 105 | J87: ='105'!Q164 -> 9849
H88: Total | J88: =sum(J85:J87) -> 29122
H89: 1931 | I89: Assoc dues | J89: 4675.89
I90: Meralco | J90: 2730.82
H91: 105 | I91: Meralco | J91: 3039.62
I92: Water plus GAF | J92: =160+952.74 -> 1112.74
H93: 1931 bidet head 345 | J93: 345
H94: 931 bidet installation 150 | J94: 150
H95: 1931 Bulb 928 | J95: 928
H96: 1931 Greasetrap 500 | J96: 500
H97: 635 Bulb c/ tech 100 | J97: 100
H98: 635 Greasetrap 500 | J98: 500
H99: 635 late check in 200 sheila? | J99: 200
H100: Total | J100: =J88-sum(J89:J99) -> 14839.93
G101: October | H101: Summary
H102: 1931 | J102: ='1931'!Q269 -> 0 | M102: 270
H103: 635 | J103: ='635'!Q203 -> 0 | M103: 6295.5
...

Sheet parking
C6: 9-11 | D6: D2 | E6: 800
C7: 11-12 | D7: D1 | E7: 400
C8: 15-16 | D8: k | E8: 350
C9: 16-17 | D9: D2 | E9: 400
C10: 17-18 | D10: D2 | E10: 400
C11: 19-20 | D11: D2 | E11: 400
C12: 20-22 | D12: D1 | E12: 900
C13: 22-24 | D13: T | E13: 800
C14: 24-25 | D14: T | E14: 400
C15: 25-26 | D15: P | E15: 350
C16: 26-27 | D16: D2 | E16: 400
C17: 27-28 | D17: k | E17: 350
C18: 29-1 | D18: Y | E18: 750
B19: NOV | C19: Total | E19: =sum(E6:E18) -> 6700
B23: Dec | C23: 45293 | D23: d1 | E23: 400
C24: 45355 | D24: d2 | E24: 350
C25: 4-9 | D25: M | E25: =800+900 -> 1700 | F25: early check out dec 8
C26: 45513 | D26: T | E26: 400 | F26: rebooked
C27: 45545 | D27: d2 | E27: 400
C28: 45577 | D28: d2 | E28: 700
C29: 45639 | D29: P | E29: 350
C30: 14-15 | D30: D2 | E30: 400
C31: 15-16 | D31: d2 | E31: 400
C32: 16-17 | D32: T | E32: 400
C33: 17-18 | D33: D2 | E33: 400
C34: 18-19 | D34: D2 | E34: 400
C35: 19-20 | D35: M, D1 | E35: 650
C36: 20-22 | D36: D1 | E36: 900
C37: 22-23 | D37: D2 | E37: 450
C38: 23-24 | D38: d2 | E38: 400
C39: 24-26 | D39: d2 | E39: 900
C40: 26-28 | D40: C | E40: 800
C41: 28-30 | D41: 1163 | E41: 900
C42: 30-31 | D42: d1 | E42: 400
C43: 31-1 | D43: d2 | E43: 950
B44: DEC | C44: Total | E44: =sum(E23:E43) -> 12650

Sheet Kristin
B3: ights Date Unit Amount Paid
B6: 1 | C6: Aug | D6: 13-14 | E6: P | F6: 300
B7: 2 | C7: Aug | D7: 25-27 | E7: D1 | F7: 600
B8: 1 | C8: Aug | D8: 45513 | E8: P | F8: 300
B9: 2 | C9: Aug | D9: 45546 | E9: P | F9: 600
B10: 1 | C10: Aug | D10: 45355 | E10: D3 | F10: 300
B11: 2 | C11: Aug | D11: 17-19 | E11: P | F11: 600
B12: 1 | C12: Aug | D12: 45418 | E12: M | F12: 300
B13: 1 | C13: Aug | D13: 13-14 | E13: M | F13: 300
B14: 1 | C14: Aug | D14: 17-18 | E14: M | F14: 300
B15: 1 | C15: Aug | D15: 17-18 | E15: D3 | F15: 300
B16: 1 | C16: Aug | D16: 12-13 | E16: D1 | F16: 300
B17: 1 | C17: Aug | D17: 15-16 | E17: P | F17: 300
B18: 1 | C18: Aug | D18: 20-21 | E18: P | F18: 300
B19: 2 | C19: Aug | D19: 22-24 | E19: D3 | F19: 600
B20: 1 | C20: Aug | D20: 30-31 | E20: P | F20: 300
B21: 1 | C21: Aug | D21: 31-sept | E21: M | F21: 300
B22: =SUM(B6:B21) -> 20 | C22: Total | F22: =SUM(F6:F21) -> 6000
C23: Incentive | F23: 1000
C24: Grand Total | F24: =SUM(F22:F23) -> 7000 | G24: Paid 9.1.24
C26: 1 Sept 1-2 P 300
C27: 2 Sept 4-6 D3 600

Sheet SALES NOTES
C2: SALE (1,500 for 2 nights) 1,800/ night | G2: Agents
B3: February | C3: Summer | D3: March to May
B4: July | C4: Rainy Days | D4: August | G4: Movie night / puzzles | H4: Agents | I4: SRP
B5: August | C5: Ber Month | D5: September | G5: Mon - Thurs
G6: Fri / Sun
G7: Saturday
C10: HOLIDAY RATE
C11: No lower than 2,500 | D11: December 15
C12: No lower than 2,500 | D12: Holy week
